{
"meta":{"test_sets":[],"test_metrics":[],"learn_metrics":[{"best_value":"Min","name":"RMSE"}],"launch_mode":"Train","parameters":"","iteration_count":1000,"learn_sets":["learn"],"name":"experiment"},
"iterations":[
{"learn":[8.389844793],"iteration":0,"passed_time":0.009311654081,"remaining_time":9.302342427},
{"learn":[8.246172312],"iteration":1,"passed_time":0.01578135872,"remaining_time":7.874898},
{"learn":[8.104693867],"iteration":2,"passed_time":0.02142218587,"remaining_time":7.119306439},
{"learn":[7.985307737],"iteration":3,"passed_time":0.02577032897,"remaining_time":6.416811913},
{"learn":[7.870963614],"iteration":4,"passed_time":0.03085637079,"remaining_time":6.140417787},
{"learn":[7.734136669],"iteration":5,"passed_time":0.0359965184,"remaining_time":5.963423215},
{"learn":[7.619144129],"iteration":6,"passed_time":0.03996436357,"remaining_time":5.669230432},
{"learn":[7.526095033],"iteration":7,"passed_time":0.04444538943,"remaining_time":5.511228289},
{"learn":[7.397592618],"iteration":8,"passed_time":0.04863596454,"remaining_time":5.355360095},
{"learn":[7.295111373],"iteration":9,"passed_time":0.05319363071,"remaining_time":5.26616944},
{"learn":[7.186788861],"iteration":10,"passed_time":0.05713499983,"remaining_time":5.136955894},
{"learn":[7.076402102],"iteration":11,"passed_time":0.06184206482,"remaining_time":5.091663337},
{"learn":[6.974123881],"iteration":12,"passed_time":0.06580539622,"remaining_time":4.996148159},
{"learn":[6.890440819],"iteration":13,"passed_time":0.07042904473,"remaining_time":4.960217007},
{"learn":[6.798680272],"iteration":14,"passed_time":0.0757277905,"remaining_time":4.972791576},
{"learn":[6.712362963],"iteration":15,"passed_time":0.0797514637,"remaining_time":4.904715018},
{"learn":[6.62053224],"iteration":16,"passed_time":0.08413826542,"remaining_time":4.865171465},
{"learn":[6.548668283],"iteration":17,"passed_time":0.08789091194,"remaining_time":4.794937529},
{"learn":[6.479473643],"iteration":18,"passed_time":0.09171601389,"remaining_time":4.735442612},
{"learn":[6.397335427],"iteration":19,"passed_time":0.09569220041,"remaining_time":4.68891782},
{"learn":[6.326489003],"iteration":20,"passed_time":0.1010959035,"remaining_time":4.71299474},
{"learn":[6.258189483],"iteration":21,"passed_time":0.1049505499,"remaining_time":4.665528992},
{"learn":[6.191579225],"iteration":22,"passed_time":0.1087446521,"remaining_time":4.6192837},
{"learn":[6.112352039],"iteration":23,"passed_time":0.1126146837,"remaining_time":4.579663805},
{"learn":[6.041018781],"iteration":24,"passed_time":0.1171241287,"remaining_time":4.567841021},
{"learn":[5.993953008],"iteration":25,"passed_time":0.1206976598,"remaining_time":4.521520024},
{"learn":[5.937289135],"iteration":26,"passed_time":0.1245023893,"remaining_time":4.486697216},
{"learn":[5.88867023],"iteration":27,"passed_time":0.1282779896,"remaining_time":4.453078782},
{"learn":[5.830194569],"iteration":28,"passed_time":0.1323494341,"remaining_time":4.431424156},
{"learn":[5.776115197],"iteration":29,"passed_time":0.1362885847,"remaining_time":4.406664239},
{"learn":[5.738287638],"iteration":30,"passed_time":0.1400408356,"remaining_time":4.377405474},
{"learn":[5.691527681],"iteration":31,"passed_time":0.1448297368,"remaining_time":4.381099537},
{"learn":[5.64352013],"iteration":32,"passed_time":0.1489474645,"remaining_time":4.364612066},
{"learn":[5.585202189],"iteration":33,"passed_time":0.1527817577,"remaining_time":4.340799351},
{"learn":[5.530651819],"iteration":34,"passed_time":0.156670115,"remaining_time":4.319618885},
{"learn":[5.480423487],"iteration":35,"passed_time":0.1605956151,"remaining_time":4.300393695},
{"learn":[5.427399879],"iteration":36,"passed_time":0.1649049816,"remaining_time":4.291986414},
{"learn":[5.391531367],"iteration":37,"passed_time":0.1684410667,"remaining_time":4.264218584},
{"learn":[5.352595339],"iteration":38,"passed_time":0.1720705342,"remaining_time":4.239994446},
{"learn":[5.315118561],"iteration":39,"passed_time":0.1759521253,"remaining_time":4.222851007},
{"learn":[5.261576866],"iteration":40,"passed_time":0.1799966248,"remaining_time":4.210164955},
{"learn":[5.216759599],"iteration":41,"passed_time":0.1840772355,"remaining_time":4.198714085},
{"learn":[5.181114149],"iteration":42,"passed_time":0.1877189313,"remaining_time":4.17783761},
{"learn":[5.145449146],"iteration":43,"passed_time":0.1918002952,"remaining_time":4.167297324},
{"learn":[5.104734575],"iteration":44,"passed_time":0.1985209041,"remaining_time":4.213054743},
{"learn":[5.074545785],"iteration":45,"passed_time":0.2025462952,"remaining_time":4.200634034},
{"learn":[5.038002584],"iteration":46,"passed_time":0.2064100259,"remaining_time":4.185292652},
{"learn":[5.005331698],"iteration":47,"passed_time":0.2106176011,"remaining_time":4.177249089},
{"learn":[4.976466817],"iteration":48,"passed_time":0.2141729219,"remaining_time":4.156703036},
{"learn":[4.949882831],"iteration":49,"passed_time":0.2179522277,"remaining_time":4.141092327},
{"learn":[4.926425069],"iteration":50,"passed_time":0.2230703754,"remaining_time":4.150858555},
{"learn":[4.906366125],"iteration":51,"passed_time":0.2284324606,"remaining_time":4.164499475},
{"learn":[4.882802386],"iteration":52,"passed_time":0.2320411155,"remaining_time":4.146093139},
{"learn":[4.859163147],"iteration":53,"passed_time":0.2358194497,"remaining_time":4.131207397},
{"learn":[4.83323499],"iteration":54,"passed_time":0.2397990063,"remaining_time":4.120182926},
{"learn":[4.799875688],"iteration":55,"passed_time":0.2447837812,"remaining_time":4.126355169},
{"learn":[4.770954487],"iteration":56,"passed_time":0.2484482416,"remaining_time":4.110292839},
{"learn":[4.745554875],"iteration":57,"passed_time":0.2521412284,"remaining_time":4.095121331},
{"learn":[4.722816713],"iteration":58,"passed_time":0.255904676,"remaining_time":4.081462713},
{"learn":[4.700625941],"iteration":59,"passed_time":0.2598822345,"remaining_time":4.07148834},
{"learn":[4.669269895],"iteration":60,"passed_time":0.2636611502,"remaining_time":4.058652787},
{"learn":[4.65298662],"iteration":61,"passed_time":0.2675550606,"remaining_time":4.047849143},
{"learn":[4.621803915],"iteration":62,"passed_time":0.2714705772,"remaining_time":4.037586204},
{"learn":[4.597074563],"iteration":63,"passed_time":0.2753282666,"remaining_time":4.026675899},
{"learn":[4.568165396],"iteration":64,"passed_time":0.2803237769,"remaining_time":4.032349714},
{"learn":[4.552296836],"iteration":65,"passed_time":0.2842942827,"remaining_time":4.023194849},
{"learn":[4.527184417],"iteration":66,"passed_time":0.2890447214,"remaining_time":4.025055598},
{"learn":[4.502124474],"iteration":67,"passed_time":0.2930402667,"remaining_time":4.01637542},
{"learn":[4.481456068],"iteration":68,"passed_time":0.2968702113,"remaining_time":4.005596619},
{"learn":[4.465467192],"iteration":69,"passed_time":0.300736891,"remaining_time":3.995504409},
{"learn":[4.447286972],"iteration":70,"passed_time":0.3050294745,"remaining_time":3.991160307},
{"learn":[4.424840603],"iteration":71,"passed_time":0.3100328107,"remaining_time":3.995978449},
{"learn":[4.410929188],"iteration":72,"passed_time":0.3137366535,"remaining_time":3.984025723},
{"learn":[4.393153914],"iteration":73,"passed_time":0.3175013561,"remaining_time":3.97305751},
{"learn":[4.366849297],"iteration":74,"passed_time":0.3218557146,"remaining_time":3.969553813},
{"learn":[4.343591294],"iteration":75,"passed_time":0.326022739,"remaining_time":3.963750143},
{"learn":[4.323689193],"iteration":76,"passed_time":0.3300102055,"remaining_time":3.955836619},
{"learn":[4.305370311],"iteration":77,"passed_time":0.3340681419,"remaining_time":3.948856754},
{"learn":[4.291030565],"iteration":78,"passed_time":0.338650865,"remaining_time":3.948068945},
{"learn":[4.270786662],"iteration":79,"passed_time":0.3425919151,"remaining_time":3.939807024},
{"learn":[4.251822716],"iteration":80,"passed_time":0.346421015,"remaining_time":3.93038164},
{"learn":[4.235705906],"iteration":81,"passed_time":0.3501884303,"remaining_time":3.920402183},
{"learn":[4.218752593],"iteration":82,"passed_time":0.3555147287,"remaining_time":3.927795256},
{"learn":[4.210244458],"iteration":83,"passed_time":0.3592129491,"remaining_time":3.917131683},
{"learn":[4.202179327],"iteration":84,"passed_time":0.3632645153,"remaining_time":3.910435664},
{"learn":[4.190458766],"iteration":85,"passed_time":0.3681174284,"remaining_time":3.912317785},
{"learn":[4.176346605],"iteration":86,"passed_time":0.3722290178,"remaining_time":3.90626544},
{"learn":[4.163334402],"iteration":87,"passed_time":0.3759592813,"remaining_time":3.896305279},
{"learn":[4.153130945],"iteration":88,"passed_time":0.3796045249,"remaining_time":3.885614856},
{"learn":[4.14166769],"iteration":89,"passed_time":0.3858166379,"remaining_time":3.901034895},
{"learn":[4.128271867],"iteration":90,"passed_time":0.389780883,"remaining_time":3.893525523},
{"learn":[4.115845167],"iteration":91,"passed_time":0.3934747352,"remaining_time":3.88342456},
{"learn":[4.098362391],"iteration":92,"passed_time":0.3975367285,"remaining_time":3.87705175},
{"learn":[4.087941795],"iteration":93,"passed_time":0.4026598008,"remaining_time":3.880955101},
{"learn":[4.074533287],"iteration":94,"passed_time":0.4063397714,"remaining_time":3.87092098},
{"learn":[4.060745746],"iteration":95,"passed_time":0.4101084,"remaining_time":3.8618541},
{"learn":[4.05223907],"iteration":96,"passed_time":0.4170055165,"remaining_time":3.882020427},
{"learn":[4.031564612],"iteration":97,"passed_time":0.4213036513,"remaining_time":3.877713199},
{"learn":[4.021571878],"iteration":98,"passed_time":0.4250269967,"remaining_time":3.86817499},
{"learn":[4.010113597],"iteration":99,"passed_time":0.4301371478,"remaining_time":3.87123433},
{"learn":[3.991950751],"iteration":100,"passed_time":0.4365528127,"remaining_time":3.885752263},
{"learn":[3.983717411],"iteration":101,"passed_time":0.4402251727,"remaining_time":3.875707893},
{"learn":[3.976274553],"iteration":102,"passed_time":0.4439138637,"remaining_time":3.865929473},
{"learn":[3.969476708],"iteration":103,"passed_time":0.4481100893,"remaining_time":3.860640769},
{"learn":[3.956098043],"iteration":104,"passed_time":0.4518979075,"remaining_time":3.851891688},
{"learn":[3.938285212],"iteration":105,"passed_time":0.4556877393,"remaining_time":3.843253198},
{"learn":[3.920244559],"iteration":106,"passed_time":0.459393318,"remaining_time":3.834002177},
{"learn":[3.906896624],"iteration":107,"passed_time":0.463587755,"remaining_time":3.828891458},
{"learn":[3.898433006],"iteration":108,"passed_time":0.4676956282,"remaining_time":3.823089951},
{"learn":[3.884475316],"iteration":109,"passed_time":0.4714190355,"remaining_time":3.81420856},
{"learn":[3.878327846],"iteration":110,"passed_time":0.475375083,"remaining_time":3.807283323},
{"learn":[3.862271707],"iteration":111,"passed_time":0.4795501594,"remaining_time":3.802147692},
{"learn":[3.850886112],"iteration":112,"passed_time":0.4834744638,"remaining_time":3.795060614},
{"learn":[3.837324769],"iteration":113,"passed_time":0.4875331649,"remaining_time":3.789073545},
{"learn":[3.829451356],"iteration":114,"passed_time":0.4912370914,"remaining_time":3.780389791},
{"learn":[3.816563014],"iteration":115,"passed_time":0.4967369378,"remaining_time":3.785478043},
{"learn":[3.80569553],"iteration":116,"passed_time":0.5018099579,"remaining_time":3.787164041},
{"learn":[3.797448059],"iteration":117,"passed_time":0.5067077608,"remaining_time":3.787425806},
{"learn":[3.786777359],"iteration":118,"passed_time":0.5110699179,"remaining_time":3.783635275},
{"learn":[3.777138087],"iteration":119,"passed_time":0.5149233759,"remaining_time":3.776104757},
{"learn":[3.75809604],"iteration":120,"passed_time":0.5186415834,"remaining_time":3.767652494},
{"learn":[3.743555494],"iteration":121,"passed_time":0.5227398778,"remaining_time":3.762013219},
{"learn":[3.732974554],"iteration":122,"passed_time":0.5270478185,"remaining_time":3.757893795},
{"learn":[3.722910867],"iteration":123,"passed_time":0.5308127973,"remaining_time":3.749935568},
{"learn":[3.705573906],"iteration":124,"passed_time":0.5346664205,"remaining_time":3.742664944},
{"learn":[3.693820128],"iteration":125,"passed_time":0.538470621,"remaining_time":3.735105736},
{"learn":[3.686248959],"iteration":126,"passed_time":0.5441743156,"remaining_time":3.740662815},
{"learn":[3.672565131],"iteration":127,"passed_time":0.5482499638,"remaining_time":3.734952878},
{"learn":[3.652925674],"iteration":128,"passed_time":0.5532108385,"remaining_time":3.735245274},
{"learn":[3.643366928],"iteration":129,"passed_time":0.5574466334,"remaining_time":3.730604393},
{"learn":[3.632133559],"iteration":130,"passed_time":0.5614946744,"remaining_time":3.724724214},
{"learn":[3.614827701],"iteration":131,"passed_time":0.5654161147,"remaining_time":3.7180393},
{"learn":[3.605215203],"iteration":132,"passed_time":0.5691320438,"remaining_time":3.710056256},
{"learn":[3.592612757],"iteration":133,"passed_time":0.5731845148,"remaining_time":3.704311865},
{"learn":[3.58642421],"iteration":134,"passed_time":0.5769700666,"remaining_time":3.696882279},
{"learn":[3.572935079],"iteration":135,"passed_time":0.5809708495,"remaining_time":3.690873632},
{"learn":[3.564652038],"iteration":136,"passed_time":0.5846353364,"remaining_time":3.682775878},
{"learn":[3.557164732],"iteration":137,"passed_time":0.5889112726,"remaining_time":3.678561717},
{"learn":[3.545109445],"iteration":138,"passed_time":0.5925725927,"remaining_time":3.670539585},
{"learn":[3.536539439],"iteration":139,"passed_time":0.5963123612,"remaining_time":3.663061647},
{"learn":[3.52734673],"iteration":140,"passed_time":0.6003852205,"remaining_time":3.657665989},
{"learn":[3.517291413],"iteration":141,"passed_time":0.6045199506,"remaining_time":3.6526628},
{"learn":[3.504920191],"iteration":142,"passed_time":0.6091229996,"remaining_time":3.650478396},
{"learn":[3.499982486],"iteration":143,"passed_time":0.6140427125,"remaining_time":3.650142791},
{"learn":[3.492400697],"iteration":144,"passed_time":0.618122467,"remaining_time":3.644791099},
{"learn":[3.486257786],"iteration":145,"passed_time":0.6220587122,"remaining_time":3.638617398},
{"learn":[3.477509108],"iteration":146,"passed_time":0.6258722074,"remaining_time":3.631761857},
{"learn":[3.466585376],"iteration":147,"passed_time":0.6296780044,"remaining_time":3.624903106},
{"learn":[3.453159288],"iteration":148,"passed_time":0.6336325126,"remaining_time":3.618934686},
{"learn":[3.446772643],"iteration":149,"passed_time":0.6378300983,"remaining_time":3.614370557},
{"learn":[3.438468049],"iteration":150,"passed_time":0.6414170719,"remaining_time":3.606378106},
{"learn":[3.429566462],"iteration":151,"passed_time":0.64503372,"remaining_time":3.598609175},
{"learn":[3.417692099],"iteration":152,"passed_time":0.6488585557,"remaining_time":3.592047037},
{"learn":[3.406919412],"iteration":153,"passed_time":0.6531854364,"remaining_time":3.588278436},
{"learn":[3.399227602],"iteration":154,"passed_time":0.657143757,"remaining_time":3.582493385},
{"learn":[3.392991976],"iteration":155,"passed_time":0.660788141,"remaining_time":3.575033276},
{"learn":[3.387660713],"iteration":156,"passed_time":0.6665060742,"remaining_time":3.578755545},
{"learn":[3.378000977],"iteration":157,"passed_time":0.672721096,"remaining_time":3.58500736},
{"learn":[3.372162933],"iteration":158,"passed_time":0.6778943144,"remaining_time":3.58559194},
{"learn":[3.366085997],"iteration":159,"passed_time":0.6816315735,"remaining_time":3.578565761},
{"learn":[3.356417855],"iteration":160,"passed_time":0.6856575541,"remaining_time":3.573085018},
{"learn":[3.348108498],"iteration":161,"passed_time":0.6895110472,"remaining_time":3.566729985},
{"learn":[3.341279088],"iteration":162,"passed_time":0.693652052,"remaining_time":3.561882009},
{"learn":[3.327077188],"iteration":163,"passed_time":0.6975936726,"remaining_time":3.556026282},
{"learn":[3.322607213],"iteration":164,"passed_time":0.7013246219,"remaining_time":3.549127632},
{"learn":[3.31512424],"iteration":165,"passed_time":0.7052008534,"remaining_time":3.542997059},
{"learn":[3.305869241],"iteration":166,"passed_time":0.7099692292,"remaining_time":3.541343521},
{"learn":[3.298101382],"iteration":167,"passed_time":0.7141049441,"remaining_time":3.536519723},
{"learn":[3.290996058],"iteration":168,"passed_time":0.7176780309,"remaining_time":3.528937537},
{"learn":[3.28295949],"iteration":169,"passed_time":0.7215550367,"remaining_time":3.522886356},
{"learn":[3.26914878],"iteration":170,"passed_time":0.7255219191,"remaining_time":3.517296321},
{"learn":[3.26264245],"iteration":171,"passed_time":0.7295906584,"remaining_time":3.512215495},
{"learn":[3.24998784],"iteration":172,"passed_time":0.7332543029,"remaining_time":3.505209876},
{"learn":[3.244824666],"iteration":173,"passed_time":0.7371706973,"remaining_time":3.499442506},
{"learn":[3.232313946],"iteration":174,"passed_time":0.7409397917,"remaining_time":3.493001875},
{"learn":[3.226731058],"iteration":175,"passed_time":0.7449437326,"remaining_time":3.487691112},
{"learn":[3.219328],"iteration":176,"passed_time":0.7487698245,"remaining_time":3.481568167},
{"learn":[3.210423326],"iteration":177,"passed_time":0.7530597116,"remaining_time":3.477612826},
{"learn":[3.203453566],"iteration":178,"passed_time":0.7566257807,"remaining_time":3.470333888},
{"learn":[3.199029552],"iteration":179,"passed_time":0.7606105239,"remaining_time":3.465003498},
{"learn":[3.194404776],"iteration":180,"passed_time":0.7642663656,"remaining_time":3.458199743},
{"learn":[3.188612196],"iteration":181,"passed_time":0.7680588411,"remaining_time":3.452044681},
{"learn":[3.18187887],"iteration":182,"passed_time":0.7718787781,"remaining_time":3.446038042},
{"learn":[3.174360022],"iteration":183,"passed_time":0.7774604791,"remaining_time":3.447868212},
{"learn":[3.167189363],"iteration":184,"passed_time":0.7815730077,"remaining_time":3.443145953},
{"learn":[3.155825077],"iteration":185,"passed_time":0.7867946423,"remaining_time":3.44328408},
{"learn":[3.144686123],"iteration":186,"passed_time":0.7907738419,"remaining_time":3.437963281},
{"learn":[3.133258955],"iteration":187,"passed_time":0.7949854465,"remaining_time":3.433660545},
{"learn":[3.125471049],"iteration":188,"passed_time":0.7989598307,"remaining_time":3.428340861},
{"learn":[3.11539468],"iteration":189,"passed_time":0.8041415291,"remaining_time":3.428182308},
{"learn":[3.109671687],"iteration":190,"passed_time":0.8099907002,"remaining_time":3.430798306},
{"learn":[3.10263659],"iteration":191,"passed_time":0.8136032959,"remaining_time":3.42391387},
{"learn":[3.099130826],"iteration":192,"passed_time":0.8175012879,"remaining_time":3.418256681},
{"learn":[3.08832786],"iteration":193,"passed_time":0.8211469979,"remaining_time":3.411569486},
{"learn":[3.08322314],"iteration":194,"passed_time":0.8256403324,"remaining_time":3.408412654},
{"learn":[3.075893949],"iteration":195,"passed_time":0.8293566222,"remaining_time":3.402054716},
{"learn":[3.064524284],"iteration":196,"passed_time":0.8329934351,"remaining_time":3.395399637},
{"learn":[3.056965719],"iteration":197,"passed_time":0.836851355,"remaining_time":3.38967064},
{"learn":[3.050049293],"iteration":198,"passed_time":0.8409579686,"remaining_time":3.384961472},
{"learn":[3.043647589],"iteration":199,"passed_time":0.8451381966,"remaining_time":3.380552786},
{"learn":[3.033475431],"iteration":200,"passed_time":0.8488550634,"remaining_time":3.374304456},
{"learn":[3.022714311],"iteration":201,"passed_time":0.8529843056,"remaining_time":3.369710277},
{"learn":[3.012359597],"iteration":202,"passed_time":0.8648554624,"remaining_time":3.395516273},
{"learn":[3.006001796],"iteration":203,"passed_time":0.8707909185,"remaining_time":3.397792015},
{"learn":[2.994975003],"iteration":204,"passed_time":0.8751928142,"remaining_time":3.394040426},
{"learn":[2.987051508],"iteration":205,"passed_time":0.8790736265,"remaining_time":3.388274075},
{"learn":[2.980126345],"iteration":206,"passed_time":0.8857695498,"remaining_time":3.393310401},
{"learn":[2.970499017],"iteration":207,"passed_time":0.9014002624,"remaining_time":3.432254845},
{"learn":[2.957382685],"iteration":208,"passed_time":0.9185751602,"remaining_time":3.4765213},
{"learn":[2.949630322],"iteration":209,"passed_time":0.9275758433,"remaining_time":3.489451982},
{"learn":[2.936915548],"iteration":210,"passed_time":0.9378556367,"remaining_time":3.506957807},
{"learn":[2.927797878],"iteration":211,"passed_time":0.9499173073,"remaining_time":3.530824708},
{"learn":[2.920331588],"iteration":212,"passed_time":0.9593406565,"remaining_time":3.544606088},
{"learn":[2.912450828],"iteration":213,"passed_time":0.967818096,"remaining_time":3.554696371},
{"learn":[2.90943348],"iteration":214,"passed_time":0.979809596,"remaining_time":3.577444339},
{"learn":[2.900639428],"iteration":215,"passed_time":0.9836131232,"remaining_time":3.570151336},
{"learn":[2.89264266],"iteration":216,"passed_time":0.9929845538,"remaining_time":3.582981132},
{"learn":[2.889025513],"iteration":217,"passed_time":1.025913981,"remaining_time":3.680113455},
{"learn":[2.879762885],"iteration":218,"passed_time":1.042637778,"remaining_time":3.718265318},
{"learn":[2.870568997],"iteration":219,"passed_time":1.049217022,"remaining_time":3.719951259},
{"learn":[2.864154463],"iteration":220,"passed_time":1.059937568,"remaining_time":3.736160026},
{"learn":[2.848760751],"iteration":221,"passed_time":1.070629641,"remaining_time":3.752026401},
{"learn":[2.840403621],"iteration":222,"passed_time":1.078918853,"remaining_time":3.759282281},
{"learn":[2.829472655],"iteration":223,"passed_time":1.089012966,"remaining_time":3.77265206},
{"learn":[2.82170715],"iteration":224,"passed_time":1.096933124,"remaining_time":3.778325205},
{"learn":[2.814016691],"iteration":225,"passed_time":1.109191643,"remaining_time":3.798735982},
{"learn":[2.809618078],"iteration":226,"passed_time":1.117493107,"remaining_time":3.805384016},
{"learn":[2.80085923],"iteration":227,"passed_time":1.122938881,"remaining_time":3.80223165},
{"learn":[2.791717011],"iteration":228,"passed_time":1.127326987,"remaining_time":3.795498285},
{"learn":[2.78239715],"iteration":229,"passed_time":1.132548808,"remaining_time":3.791576446},
{"learn":[2.774930981],"iteration":230,"passed_time":1.136755357,"remaining_time":3.784263505},
{"learn":[2.768074151],"iteration":231,"passed_time":1.140796503,"remaining_time":3.776429803},
{"learn":[2.759741541],"iteration":232,"passed_time":1.145253967,"remaining_time":3.769999112},
{"learn":[2.749948584],"iteration":233,"passed_time":1.149351144,"remaining_time":3.762405883},
{"learn":[2.747298558],"iteration":234,"passed_time":1.155615774,"remaining_time":3.761898159},
{"learn":[2.741270619],"iteration":235,"passed_time":1.161624144,"remaining_time":3.760512059},
{"learn":[2.733723858],"iteration":236,"passed_time":1.167841727,"remaining_time":3.759760497},
{"learn":[2.725442776],"iteration":237,"passed_time":1.174346212,"remaining_time":3.759881568},
{"learn":[2.718402379],"iteration":238,"passed_time":1.179129461,"remaining_time":3.754466611},
{"learn":[2.709168827],"iteration":239,"passed_time":1.185244723,"remaining_time":3.753274955},
{"learn":[2.70177929],"iteration":240,"passed_time":1.190301262,"remaining_time":3.748708123},
{"learn":[2.699680486],"iteration":241,"passed_time":1.194722732,"remaining_time":3.742148062},
{"learn":[2.690166853],"iteration":242,"passed_time":1.198719337,"remaining_time":3.734282049},
{"learn":[2.681869838],"iteration":243,"passed_time":1.203374601,"remaining_time":3.728488518},
{"learn":[2.675024571],"iteration":244,"passed_time":1.213832035,"remaining_time":3.740584434},
{"learn":[2.669502761],"iteration":245,"passed_time":1.217838031,"remaining_time":3.732723072},
{"learn":[2.660418571],"iteration":246,"passed_time":1.222264881,"remaining_time":3.726175934},
{"learn":[2.654479352],"iteration":247,"passed_time":1.227382747,"remaining_time":3.721741233},
{"learn":[2.644105432],"iteration":248,"passed_time":1.231580966,"remaining_time":3.714527332},
{"learn":[2.638192207],"iteration":249,"passed_time":1.23538895,"remaining_time":3.706166849},
{"learn":[2.630909875],"iteration":250,"passed_time":1.23901608,"remaining_time":3.697302965},
{"learn":[2.618229597],"iteration":251,"passed_time":1.24347936,"remaining_time":3.690962545},
{"learn":[2.611713115],"iteration":252,"passed_time":1.247800998,"remaining_time":3.684218758},
{"learn":[2.606565262],"iteration":253,"passed_time":1.251795445,"remaining_time":3.676533078},
{"learn":[2.596538962],"iteration":254,"passed_time":1.255526691,"remaining_time":3.668107391},
{"learn":[2.589423118],"iteration":255,"passed_time":1.259458127,"remaining_time":3.660300183},
{"learn":[2.583680259],"iteration":256,"passed_time":1.263592577,"remaining_time":3.653110056},
{"learn":[2.576628976],"iteration":257,"passed_time":1.269075289,"remaining_time":3.649821181},
{"learn":[2.570148034],"iteration":258,"passed_time":1.272762162,"remaining_time":3.64137746},
{"learn":[2.566754916],"iteration":259,"passed_time":1.276950621,"remaining_time":3.634397921},
{"learn":[2.559159777],"iteration":260,"passed_time":1.282715431,"remaining_time":3.631903079},
{"learn":[2.55546054],"iteration":261,"passed_time":1.286545254,"remaining_time":3.623932815},
{"learn":[2.55213991],"iteration":262,"passed_time":1.29101488,"remaining_time":3.617786945},
{"learn":[2.545441099],"iteration":263,"passed_time":1.294715727,"remaining_time":3.60951051},
{"learn":[2.537682397],"iteration":264,"passed_time":1.299694763,"remaining_time":3.604813776},
{"learn":[2.529908274],"iteration":265,"passed_time":1.303467342,"remaining_time":3.596785824},
{"learn":[2.523634833],"iteration":266,"passed_time":1.30841821,"remaining_time":3.592024523},
{"learn":[2.521121584],"iteration":267,"passed_time":1.31205514,"remaining_time":3.583672995},
{"learn":[2.514904458],"iteration":268,"passed_time":1.316250362,"remaining_time":3.576873659},
{"learn":[2.509213678],"iteration":269,"passed_time":1.319886805,"remaining_time":3.568582843},
{"learn":[2.506908972],"iteration":270,"passed_time":1.324189239,"remaining_time":3.562117916},
{"learn":[2.502728127],"iteration":271,"passed_time":1.32822672,"remaining_time":3.55495975},
{"learn":[2.49705136],"iteration":272,"passed_time":1.332006546,"remaining_time":3.547138312},
{"learn":[2.491465435],"iteration":273,"passed_time":1.33607356,"remaining_time":3.540107315},
{"learn":[2.485998316],"iteration":274,"passed_time":1.340040215,"remaining_time":3.532833295},
{"learn":[2.478281311],"iteration":275,"passed_time":1.344030116,"remaining_time":3.525644217},
{"learn":[2.471108581],"iteration":276,"passed_time":1.347848967,"remaining_time":3.51803178},
{"learn":[2.463061788],"iteration":277,"passed_time":1.351779753,"remaining_time":3.510737344},
{"learn":[2.453297864],"iteration":278,"passed_time":1.355736064,"remaining_time":3.503532981},
{"learn":[2.44799459],"iteration":279,"passed_time":1.359585708,"remaining_time":3.496077536},
{"learn":[2.441165829],"iteration":280,"passed_time":1.363452971,"remaining_time":3.488692832},
{"learn":[2.436314047],"iteration":281,"passed_time":1.367241894,"remaining_time":3.481133617},
{"learn":[2.431092174],"iteration":282,"passed_time":1.371730776,"remaining_time":3.475374438},
{"learn":[2.423410854],"iteration":283,"passed_time":1.375493754,"remaining_time":3.467794113},
{"learn":[2.417948652],"iteration":284,"passed_time":1.379242816,"remaining_time":3.460205662},
{"learn":[2.410212021],"iteration":285,"passed_time":1.383437861,"remaining_time":3.453757456},
{"learn":[2.403102819],"iteration":286,"passed_time":1.387066718,"remaining_time":3.445918362},
{"learn":[2.397274463],"iteration":287,"passed_time":1.394072729,"remaining_time":3.44645758},
{"learn":[2.390417242],"iteration":288,"passed_time":1.39861685,"remaining_time":3.440887821},
{"learn":[2.386597056],"iteration":289,"passed_time":1.402981058,"remaining_time":3.434884659},
{"learn":[2.379124309],"iteration":290,"passed_time":1.406676902,"remaining_time":3.427264342},
{"learn":[2.374950876],"iteration":291,"passed_time":1.410435707,"remaining_time":3.419823563},
{"learn":[2.370214167],"iteration":292,"passed_time":1.415666521,"remaining_time":3.415959831},
{"learn":[2.364653036],"iteration":293,"passed_time":1.420201204,"remaining_time":3.410415136},
{"learn":[2.360155466],"iteration":294,"passed_time":1.423990759,"remaining_time":3.403096561},
{"learn":[2.355600392],"iteration":295,"passed_time":1.42775946,"remaining_time":3.39575223},
{"learn":[2.349884725],"iteration":296,"passed_time":1.432517242,"remaining_time":3.390773136},
{"learn":[2.345707854],"iteration":297,"passed_time":1.436913435,"remaining_time":3.384943731},
{"learn":[2.340106794],"iteration":298,"passed_time":1.441194615,"remaining_time":3.378854266},
{"learn":[2.33715304],"iteration":299,"passed_time":1.444927807,"remaining_time":3.371498217},
{"learn":[2.332074727],"iteration":300,"passed_time":1.449274139,"remaining_time":3.365590109},
{"learn":[2.326151673],"iteration":301,"passed_time":1.452935257,"remaining_time":3.358108641},
{"learn":[2.319210262],"iteration":302,"passed_time":1.4568071,"remaining_time":3.351137124},
{"learn":[2.314325121],"iteration":303,"passed_time":1.461187298,"remaining_time":3.345349867},
{"learn":[2.309885521],"iteration":304,"passed_time":1.46551446,"remaining_time":3.339450983},
{"learn":[2.30751709],"iteration":305,"passed_time":1.469633471,"remaining_time":3.33309029},
{"learn":[2.304341182],"iteration":306,"passed_time":1.473328717,"remaining_time":3.325787624},
{"learn":[2.297973382],"iteration":307,"passed_time":1.477156131,"remaining_time":3.318805333},
{"learn":[2.295130557],"iteration":308,"passed_time":1.481971301,"remaining_time":3.314052328},
{"learn":[2.2893572],"iteration":309,"passed_time":1.485728108,"remaining_time":3.306943209},
{"learn":[2.283124298],"iteration":310,"passed_time":1.489550815,"remaining_time":3.300001644},
{"learn":[2.279055172],"iteration":311,"passed_time":1.493385383,"remaining_time":3.293106229},
{"learn":[2.274735995],"iteration":312,"passed_time":1.497690908,"remaining_time":3.28726407},
{"learn":[2.269612849],"iteration":313,"passed_time":1.503277323,"remaining_time":3.284230075},
{"learn":[2.263869831],"iteration":314,"passed_time":1.50872046,"remaining_time":3.280868303},
{"learn":[2.258662914],"iteration":315,"passed_time":1.512933413,"remaining_time":3.274830551},
{"learn":[2.25530526],"iteration":316,"passed_time":1.517105826,"remaining_time":3.268716969},
{"learn":[2.249253315],"iteration":317,"passed_time":1.521862547,"remaining_time":3.263868732},
{"learn":[2.247477268],"iteration":318,"passed_time":1.525746404,"remaining_time":3.257157683},
{"learn":[2.246906762],"iteration":319,"passed_time":1.529468405,"remaining_time":3.25012036},
{"learn":[2.240881694],"iteration":320,"passed_time":1.53312366,"remaining_time":3.242962507},
{"learn":[2.237902861],"iteration":321,"passed_time":1.537603514,"remaining_time":3.237562679},
{"learn":[2.235198395],"iteration":322,"passed_time":1.541516844,"remaining_time":3.230981125},
{"learn":[2.231244648],"iteration":323,"passed_time":1.5457447,"remaining_time":3.225072276},
{"learn":[2.226961699],"iteration":324,"passed_time":1.549505971,"remaining_time":3.218204709},
{"learn":[2.220575998],"iteration":325,"passed_time":1.553588337,"remaining_time":3.212020058},
{"learn":[2.216457693],"iteration":326,"passed_time":1.557787773,"remaining_time":3.206089208},
{"learn":[2.211189917],"iteration":327,"passed_time":1.561453387,"remaining_time":3.199075232},
{"learn":[2.208186597],"iteration":328,"passed_time":1.565211581,"remaining_time":3.192270429},
{"learn":[2.207234259],"iteration":329,"passed_time":1.568745423,"remaining_time":3.185028585},
{"learn":[2.206763721],"iteration":330,"passed_time":1.572665831,"remaining_time":3.178590456},
{"learn":[2.202957254],"iteration":331,"passed_time":1.576433061,"remaining_time":3.171859291},
{"learn":[2.201081789],"iteration":332,"passed_time":1.580854666,"remaining_time":3.166456644},
{"learn":[2.198123701],"iteration":333,"passed_time":1.584502745,"remaining_time":3.159517449},
{"learn":[2.197430525],"iteration":334,"passed_time":1.588344141,"remaining_time":3.152981654},
{"learn":[2.193593896],"iteration":335,"passed_time":1.592650207,"remaining_time":3.147380171},
{"learn":[2.190180846],"iteration":336,"passed_time":1.596514011,"remaining_time":3.140916288},
{"learn":[2.185683327],"iteration":337,"passed_time":1.600326434,"remaining_time":3.134367157},
{"learn":[2.184269508],"iteration":338,"passed_time":1.60437079,"remaining_time":3.128286407},
{"learn":[2.183839919],"iteration":339,"passed_time":1.611233703,"remaining_time":3.127688954},
{"learn":[2.182595652],"iteration":340,"passed_time":1.615185018,"remaining_time":3.121427939},
{"learn":[2.179676808],"iteration":341,"passed_time":1.619331079,"remaining_time":3.115555118},
{"learn":[2.176424871],"iteration":342,"passed_time":1.623375259,"remaining_time":3.109497216},
{"learn":[2.169538104],"iteration":343,"passed_time":1.631397342,"remaining_time":3.111036792},
{"learn":[2.167897129],"iteration":344,"passed_time":1.635389039,"remaining_time":3.104869045},
{"learn":[2.164656826],"iteration":345,"passed_time":1.63957445,"remaining_time":3.09908003},
{"learn":[2.163021421],"iteration":346,"passed_time":1.643280712,"remaining_time":3.092398572},
{"learn":[2.157145249],"iteration":347,"passed_time":1.64700246,"remaining_time":3.08576323},
{"learn":[2.152044738],"iteration":348,"passed_time":1.650689495,"remaining_time":3.079079832},
{"learn":[2.146421791],"iteration":349,"passed_time":1.654843556,"remaining_time":3.07328089},
{"learn":[2.145637371],"iteration":350,"passed_time":1.658900392,"remaining_time":3.067311551},
{"learn":[2.142434445],"iteration":351,"passed_time":1.663719132,"remaining_time":3.062755676},
{"learn":[2.138402734],"iteration":352,"passed_time":1.668137605,"remaining_time":3.057464676},
{"learn":[2.133186779],"iteration":353,"passed_time":1.67189834,"remaining_time":3.050978326},
{"learn":[2.12580905],"iteration":354,"passed_time":1.675894054,"remaining_time":3.044934267},
{"learn":[2.123463042],"iteration":355,"passed_time":1.679597745,"remaining_time":3.038373448},
{"learn":[2.122729132],"iteration":356,"passed_time":1.683777434,"remaining_time":3.032685966},
{"learn":[2.122148635],"iteration":357,"passed_time":1.687787579,"remaining_time":3.026702865},
{"learn":[2.118182149],"iteration":358,"passed_time":1.691591955,"remaining_time":3.020363351},
{"learn":[2.117204834],"iteration":359,"passed_time":1.695459828,"remaining_time":3.014150806},
{"learn":[2.116494166],"iteration":360,"passed_time":1.699441565,"remaining_time":3.008152798},
{"learn":[2.112446436],"iteration":361,"passed_time":1.703167654,"remaining_time":3.001715369},
{"learn":[2.10793486],"iteration":362,"passed_time":1.707436985,"remaining_time":2.99624617},
{"learn":[2.103917049],"iteration":363,"passed_time":1.711200698,"remaining_time":2.989900121},
{"learn":[2.098579936],"iteration":364,"passed_time":1.715477595,"remaining_time":2.984461022},
{"learn":[2.09518484],"iteration":365,"passed_time":1.719137982,"remaining_time":2.97796033},
{"learn":[2.094637679],"iteration":366,"passed_time":1.723349092,"remaining_time":2.972425001},
{"learn":[2.090015966],"iteration":367,"passed_time":1.72719018,"remaining_time":2.966261396},
{"learn":[2.089642754],"iteration":368,"passed_time":1.731964089,"remaining_time":2.961705529},
{"learn":[2.085016519],"iteration":369,"passed_time":1.736049269,"remaining_time":2.955975783},
{"learn":[2.079247985],"iteration":370,"passed_time":1.739808313,"remaining_time":2.949701965},
{"learn":[2.074846943],"iteration":371,"passed_time":1.745434936,"remaining_time":2.946594462},
{"learn":[2.070425161],"iteration":372,"passed_time":1.749548142,"remaining_time":2.94092945},
{"learn":[2.066162533],"iteration":373,"passed_time":1.753577484,"remaining_time":2.935132366},
{"learn":[2.062352947],"iteration":374,"passed_time":1.75739239,"remaining_time":2.928987317},
{"learn":[2.061716791],"iteration":375,"passed_time":1.761358381,"remaining_time":2.923105398},
{"learn":[2.058790921],"iteration":376,"passed_time":1.765310267,"remaining_time":2.917210336},
{"learn":[2.054414006],"iteration":377,"passed_time":1.769045257,"remaining_time":2.91096865},
{"learn":[2.048571925],"iteration":378,"passed_time":1.772844589,"remaining_time":2.90484562},
{"learn":[2.046313159],"iteration":379,"passed_time":1.776673959,"remaining_time":2.898783827},
{"learn":[2.043185697],"iteration":380,"passed_time":1.781225263,"remaining_time":2.893906661},
{"learn":[2.039390089],"iteration":381,"passed_time":1.784898265,"remaining_time":2.887610281},
{"learn":[2.032999091],"iteration":382,"passed_time":1.788654436,"remaining_time":2.881461585},
{"learn":[2.027906232],"iteration":383,"passed_time":1.792406899,"remaining_time":2.8753194},
{"learn":[2.021432501],"iteration":384,"passed_time":1.796852672,"remaining_time":2.870297126},
{"learn":[2.018934471],"iteration":385,"passed_time":1.800767803,"remaining_time":2.864433759},
{"learn":[2.014454946],"iteration":386,"passed_time":1.805455051,"remaining_time":2.859803478},
{"learn":[2.009987014],"iteration":387,"passed_time":1.81091504,"remaining_time":2.856391764},
{"learn":[2.005988967],"iteration":388,"passed_time":1.814901877,"remaining_time":2.850655648},
{"learn":[2.002364456],"iteration":389,"passed_time":1.818788638,"remaining_time":2.844771972},
{"learn":[1.999713026],"iteration":390,"passed_time":1.822414392,"remaining_time":2.838491982},
{"learn":[1.994465077],"iteration":391,"passed_time":1.826624247,"remaining_time":2.833131485},
{"learn":[1.988672803],"iteration":392,"passed_time":1.83043551,"remaining_time":2.827161207},
{"learn":[1.983501185],"iteration":393,"passed_time":1.834404531,"remaining_time":2.821444532},
{"learn":[1.98140766],"iteration":394,"passed_time":1.838088182,"remaining_time":2.81529962},
{"learn":[1.978439259],"iteration":395,"passed_time":1.842221665,"remaining_time":2.809853246},
{"learn":[1.973121841],"iteration":396,"passed_time":1.846502132,"remaining_time":2.804636739},
{"learn":[1.967759059],"iteration":397,"passed_time":1.850332362,"remaining_time":2.798743925},
{"learn":[1.962676373],"iteration":398,"passed_time":1.854121202,"remaining_time":2.792799104},
{"learn":[1.958399598],"iteration":399,"passed_time":1.859034526,"remaining_time":2.78855179},
{"learn":[1.955841809],"iteration":400,"passed_time":1.865278972,"remaining_time":2.786289537},
{"learn":[1.952081359],"iteration":401,"passed_time":1.869114707,"remaining_time":2.780424366},
{"learn":[1.946313958],"iteration":402,"passed_time":1.873004146,"remaining_time":2.774648822},
{"learn":[1.944396511],"iteration":403,"passed_time":1.877228468,"remaining_time":2.769376651},
{"learn":[1.939601976],"iteration":404,"passed_time":1.88087199,"remaining_time":2.76325638},
{"learn":[1.935359307],"iteration":405,"passed_time":1.885123688,"remaining_time":2.758038106},
{"learn":[1.931132687],"iteration":406,"passed_time":1.888832329,"remaining_time":2.752033344},
{"learn":[1.928671052],"iteration":407,"passed_time":1.892668163,"remaining_time":2.746224394},
{"learn":[1.92128945],"iteration":408,"passed_time":1.896853257,"remaining_time":2.740929767},
{"learn":[1.918407204],"iteration":409,"passed_time":1.900452169,"remaining_time":2.734797024},
{"learn":[1.914091974],"iteration":410,"passed_time":1.905320386,"remaining_time":2.730495638},
{"learn":[1.909403797],"iteration":411,"passed_time":1.910349559,"remaining_time":2.726421216},
{"learn":[1.904864478],"iteration":412,"passed_time":1.914419877,"remaining_time":2.720979341},
{"learn":[1.902588208],"iteration":413,"passed_time":1.917984955,"remaining_time":2.714828947},
{"learn":[1.899386072],"iteration":414,"passed_time":1.923959741,"remaining_time":2.712087827},
{"learn":[1.89650394],"iteration":415,"passed_time":1.927792118,"remaining_time":2.70632355},
{"learn":[1.893244304],"iteration":416,"passed_time":1.931419683,"remaining_time":2.700282194},
{"learn":[1.888817884],"iteration":417,"passed_time":1.935189832,"remaining_time":2.694450914},
{"learn":[1.885617142],"iteration":418,"passed_time":1.940471468,"remaining_time":2.690725353},
{"learn":[1.881975701],"iteration":419,"passed_time":1.944222886,"remaining_time":2.684879224},
{"learn":[1.877881622],"iteration":420,"passed_time":1.947925563,"remaining_time":2.678976012},
{"learn":[1.875277979],"iteration":421,"passed_time":1.952871919,"remaining_time":2.674786657},
{"learn":[1.872125437],"iteration":422,"passed_time":1.957657291,"remaining_time":2.67037413},
{"learn":[1.866642519],"iteration":423,"passed_time":1.961818719,"remaining_time":2.665112222},
{"learn":[1.86351766],"iteration":424,"passed_time":1.965668315,"remaining_time":2.659433603},
{"learn":[1.859900717],"iteration":425,"passed_time":1.970127633,"remaining_time":2.654585121},
{"learn":[1.856637354],"iteration":426,"passed_time":1.975127012,"remaining_time":2.65046318},
{"learn":[1.856086675],"iteration":427,"passed_time":1.980018264,"remaining_time":2.646192633},
{"learn":[1.853932146],"iteration":428,"passed_time":1.984118659,"remaining_time":2.64086656},
{"learn":[1.850277902],"iteration":429,"passed_time":1.987894051,"remaining_time":2.63511537},
{"learn":[1.845777827],"iteration":430,"passed_time":1.991952048,"remaining_time":2.629746439},
{"learn":[1.841366654],"iteration":431,"passed_time":1.995892114,"remaining_time":2.62422852},
{"learn":[1.837518825],"iteration":432,"passed_time":2.001530894,"remaining_time":2.620942302},
{"learn":[1.831074401],"iteration":433,"passed_time":2.005699028,"remaining_time":2.615727304},
{"learn":[1.827832719],"iteration":434,"passed_time":2.009927404,"remaining_time":2.610595363},
{"learn":[1.825159407],"iteration":435,"passed_time":2.013706829,"remaining_time":2.604886816},
{"learn":[1.821827826],"iteration":436,"passed_time":2.018353759,"remaining_time":2.600304728},
{"learn":[1.820054982],"iteration":437,"passed_time":2.022017565,"remaining_time":2.594460893},
{"learn":[1.815864979],"iteration":438,"passed_time":2.025863776,"remaining_time":2.588860087},
{"learn":[1.814827513],"iteration":439,"passed_time":2.029898075,"remaining_time":2.583506641},
{"learn":[1.811061278],"iteration":440,"passed_time":2.034672672,"remaining_time":2.579097559},
{"learn":[1.80764161],"iteration":441,"passed_time":2.038637259,"remaining_time":2.573664231},
{"learn":[1.804839928],"iteration":442,"passed_time":2.042430937,"remaining_time":2.568022645},
{"learn":[1.801943218],"iteration":443,"passed_time":2.04685419,"remaining_time":2.563177769},
{"learn":[1.798376231],"iteration":444,"passed_time":2.050536633,"remaining_time":2.557410857},
{"learn":[1.795044214],"iteration":445,"passed_time":2.054297143,"remaining_time":2.551750263},
{"learn":[1.791943957],"iteration":446,"passed_time":2.058213382,"remaining_time":2.546290829},
{"learn":[1.790774769],"iteration":447,"passed_time":2.063890332,"remaining_time":2.54300773},
{"learn":[1.788969107],"iteration":448,"passed_time":2.067653495,"remaining_time":2.537365425},
{"learn":[1.788121131],"iteration":449,"passed_time":2.071331266,"remaining_time":2.531627102},
{"learn":[1.784022047],"iteration":450,"passed_time":2.075244707,"remaining_time":2.526184798},
{"learn":[1.780080481],"iteration":451,"passed_time":2.079534527,"remaining_time":2.521205577},
{"learn":[1.777951293],"iteration":452,"passed_time":2.083208908,"remaining_time":2.515486254},
{"learn":[1.773980329],"iteration":453,"passed_time":2.086900624,"remaining_time":2.509796786},
{"learn":[1.771457015],"iteration":454,"passed_time":2.090701737,"remaining_time":2.504247136},
{"learn":[1.766691686],"iteration":455,"passed_time":2.094924048,"remaining_time":2.499207636},
{"learn":[1.765989139],"iteration":456,"passed_time":2.098494039,"remaining_time":2.493396637},
{"learn":[1.761020757],"iteration":457,"passed_time":2.104873811,"remaining_time":2.490920536},
{"learn":[1.758197107],"iteration":458,"passed_time":2.10869593,"remaining_time":2.48541285},
{"learn":[1.754350543],"iteration":459,"passed_time":2.112746827,"remaining_time":2.480181058},
{"learn":[1.751342304],"iteration":460,"passed_time":2.116362307,"remaining_time":2.4744453},
{"learn":[1.748605422],"iteration":461,"passed_time":2.120327155,"remaining_time":2.469125561},
{"learn":[1.748054207],"iteration":462,"passed_time":2.125237026,"remaining_time":2.464907738},
{"learn":[1.74448736],"iteration":463,"passed_time":2.130053211,"remaining_time":2.46057871},
{"learn":[1.739580582],"iteration":464,"passed_time":2.133967029,"remaining_time":2.455209378},
{"learn":[1.737111746],"iteration":465,"passed_time":2.137593273,"remaining_time":2.449516755},
{"learn":[1.733682001],"iteration":466,"passed_time":2.141921461,"remaining_time":2.44463413},
{"learn":[1.731185726],"iteration":467,"passed_time":2.145673902,"remaining_time":2.439099393},
{"learn":[1.726211953],"iteration":468,"passed_time":2.149693456,"remaining_time":2.433874681},
{"learn":[1.723371621],"iteration":469,"passed_time":2.153456065,"remaining_time":2.42836535},
{"learn":[1.72060466],"iteration":470,"passed_time":2.15743077,"remaining_time":2.423101651},
{"learn":[1.717413555],"iteration":471,"passed_time":2.161502342,"remaining_time":2.417951772},
{"learn":[1.715856953],"iteration":472,"passed_time":2.165311468,"remaining_time":2.412514045},
{"learn":[1.714835727],"iteration":473,"passed_time":2.169111142,"remaining_time":2.407072702},
{"learn":[1.712504152],"iteration":474,"passed_time":2.173100144,"remaining_time":2.401847528},
{"learn":[1.709237017],"iteration":475,"passed_time":2.176784811,"remaining_time":2.396292523},
{"learn":[1.70366488],"iteration":476,"passed_time":2.180966106,"remaining_time":2.391289881},
{"learn":[1.703029154],"iteration":477,"passed_time":2.184530349,"remaining_time":2.385616824},
{"learn":[1.69707065],"iteration":478,"passed_time":2.188869359,"remaining_time":2.380795274},
{"learn":[1.69294262],"iteration":479,"passed_time":2.193670704,"remaining_time":2.376476597},
{"learn":[1.690814639],"iteration":480,"passed_time":2.199207599,"remaining_time":2.372949571},
{"learn":[1.688470051],"iteration":481,"passed_time":2.202994897,"remaining_time":2.367533935},
{"learn":[1.685774956],"iteration":482,"passed_time":2.207469283,"remaining_time":2.362860496},
{"learn":[1.682938685],"iteration":483,"passed_time":2.211104525,"remaining_time":2.357293253},
{"learn":[1.678132972],"iteration":484,"passed_time":2.215469142,"remaining_time":2.35250847},
{"learn":[1.675425169],"iteration":485,"passed_time":2.21979966,"remaining_time":2.347689353},
{"learn":[1.671690434],"iteration":486,"passed_time":2.22430155,"remaining_time":2.343052762},
{"learn":[1.668252618],"iteration":487,"passed_time":2.228005573,"remaining_time":2.337579617},
{"learn":[1.666440966],"iteration":488,"passed_time":2.231887593,"remaining_time":2.332299714},
{"learn":[1.662677069],"iteration":489,"passed_time":2.236892107,"remaining_time":2.328193826},
{"learn":[1.661018242],"iteration":490,"passed_time":2.240595597,"remaining_time":2.322735558},
{"learn":[1.658633097],"iteration":491,"passed_time":2.245113826,"remaining_time":2.318125658},
{"learn":[1.658191725],"iteration":492,"passed_time":2.248884944,"remaining_time":2.312747803},
{"learn":[1.654449097],"iteration":493,"passed_time":2.254776056,"remaining_time":2.309547944},
{"learn":[1.652066625],"iteration":494,"passed_time":2.258400898,"remaining_time":2.304025159},
{"learn":[1.649848181],"iteration":495,"passed_time":2.262153327,"remaining_time":2.298639671},
{"learn":[1.645790179],"iteration":496,"passed_time":2.265721908,"remaining_time":2.293074688},
{"learn":[1.642851043],"iteration":497,"passed_time":2.270066096,"remaining_time":2.288299558},
{"learn":[1.639293691],"iteration":498,"passed_time":2.274278519,"remaining_time":2.283393863},
{"learn":[1.637794086],"iteration":499,"passed_time":2.277958924,"remaining_time":2.277958924},
{"learn":[1.634585438],"iteration":500,"passed_time":2.281989859,"remaining_time":2.272880119},
{"learn":[1.632393112],"iteration":501,"passed_time":2.285969622,"remaining_time":2.267754725},
{"learn":[1.625903099],"iteration":502,"passed_time":2.289710842,"remaining_time":2.262398188},
{"learn":[1.624667568],"iteration":503,"passed_time":2.293894357,"remaining_time":2.257483335},
{"learn":[1.620634733],"iteration":504,"passed_time":2.298379275,"remaining_time":2.252866814},
{"learn":[1.618947948],"iteration":505,"passed_time":2.302959418,"remaining_time":2.24834378},
{"learn":[1.618452275],"iteration":506,"passed_time":2.306647236,"remaining_time":2.242952835},
{"learn":[1.614574127],"iteration":507,"passed_time":2.310669723,"remaining_time":2.237892724},
{"learn":[1.612214038],"iteration":508,"passed_time":2.314523584,"remaining_time":2.232674027},
{"learn":[1.609526182],"iteration":509,"passed_time":2.318138226,"remaining_time":2.227230845},
{"learn":[1.6074125],"iteration":510,"passed_time":2.322505445,"remaining_time":2.222514995},
{"learn":[1.605610254],"iteration":511,"passed_time":2.326527011,"remaining_time":2.217471058},
{"learn":[1.605283332],"iteration":512,"passed_time":2.33076661,"remaining_time":2.212638088},
{"learn":[1.599994889],"iteration":513,"passed_time":2.334531521,"remaining_time":2.207358597},
{"learn":[1.598309723],"iteration":514,"passed_time":2.341192918,"remaining_time":2.204812748},
{"learn":[1.59398012],"iteration":515,"passed_time":2.34505532,"remaining_time":2.199625533},
{"learn":[1.591670841],"iteration":516,"passed_time":2.349069151,"remaining_time":2.194584913},
{"learn":[1.58828254],"iteration":517,"passed_time":2.352685871,"remaining_time":2.189178745},
{"learn":[1.587880061],"iteration":518,"passed_time":2.356479552,"remaining_time":2.183943477},
{"learn":[1.587589944],"iteration":519,"passed_time":2.360092338,"remaining_time":2.178546773},
{"learn":[1.586869533],"iteration":520,"passed_time":2.364224057,"remaining_time":2.173634018},
{"learn":[1.583212454],"iteration":521,"passed_time":2.368484731,"remaining_time":2.16884234},
{"learn":[1.579351639],"iteration":522,"passed_time":2.372215636,"remaining_time":2.163569518},
{"learn":[1.57719076],"iteration":523,"passed_time":2.376063408,"remaining_time":2.158408744},
{"learn":[1.576871838],"iteration":524,"passed_time":2.379822084,"remaining_time":2.153172362},
{"learn":[1.57234311],"iteration":525,"passed_time":2.384402986,"remaining_time":2.148682539},
{"learn":[1.569141014],"iteration":526,"passed_time":2.389477002,"remaining_time":2.144634957},
{"learn":[1.564605907],"iteration":527,"passed_time":2.393721174,"remaining_time":2.139841656},
{"learn":[1.561927705],"iteration":528,"passed_time":2.397866793,"remaining_time":2.134962684},
{"learn":[1.559963569],"iteration":529,"passed_time":2.401395796,"remaining_time":2.129539668},
{"learn":[1.556786221],"iteration":530,"passed_time":2.405312924,"remaining_time":2.124466594},
{"learn":[1.554600751],"iteration":531,"passed_time":2.409307564,"remaining_time":2.119466053},
{"learn":[1.552082728],"iteration":532,"passed_time":2.412880984,"remaining_time":2.114100225},
{"learn":[1.551017928],"iteration":533,"passed_time":2.416895406,"remaining_time":2.109125954},
{"learn":[1.548283997],"iteration":534,"passed_time":2.42063523,"remaining_time":2.103916602},
{"learn":[1.545201378],"iteration":535,"passed_time":2.424835217,"remaining_time":2.099111083},
{"learn":[1.543555439],"iteration":536,"passed_time":2.428573921,"remaining_time":2.093910103},
{"learn":[1.54304525],"iteration":537,"passed_time":2.43340776,"remaining_time":2.089654991},
{"learn":[1.539738294],"iteration":538,"passed_time":2.437336288,"remaining_time":2.08462343},
{"learn":[1.53771384],"iteration":539,"passed_time":2.441493322,"remaining_time":2.079790608},
{"learn":[1.537130273],"iteration":540,"passed_time":2.446455136,"remaining_time":2.075643082},
{"learn":[1.535704264],"iteration":541,"passed_time":2.450099344,"remaining_time":2.070379151},
{"learn":[1.532953212],"iteration":542,"passed_time":2.455332137,"remaining_time":2.066458171},
{"learn":[1.530275682],"iteration":543,"passed_time":2.460067325,"remaining_time":2.062115258},
{"learn":[1.530016742],"iteration":544,"passed_time":2.463874879,"remaining_time":2.056996458},
{"learn":[1.527890412],"iteration":545,"passed_time":2.467607195,"remaining_time":2.051819902},
{"learn":[1.524671753],"iteration":546,"passed_time":2.471929738,"remaining_time":2.047137425},
{"learn":[1.520357727],"iteration":547,"passed_time":2.475708348,"remaining_time":2.042007616},
{"learn":[1.516466341],"iteration":548,"passed_time":2.479475563,"remaining_time":2.036873367},
{"learn":[1.514233412],"iteration":549,"passed_time":2.483336968,"remaining_time":2.031821156},
{"learn":[1.51259124],"iteration":550,"passed_time":2.487564492,"remaining_time":2.02707161},
{"learn":[1.51101801],"iteration":551,"passed_time":2.491728382,"remaining_time":2.02227231},
{"learn":[1.510474903],"iteration":552,"passed_time":2.495242707,"remaining_time":2.016950254},
{"learn":[1.508241626],"iteration":553,"passed_time":2.499012515,"remaining_time":2.0118404},
{"learn":[1.507491496],"iteration":554,"passed_time":2.503048281,"remaining_time":2.006948622},
{"learn":[1.506277861],"iteration":555,"passed_time":2.506723643,"remaining_time":2.001772118},
{"learn":[1.501381439],"iteration":556,"passed_time":2.510727434,"remaining_time":1.996862214},
{"learn":[1.496958691],"iteration":557,"passed_time":2.514506498,"remaining_time":1.991777549},
{"learn":[1.49353387],"iteration":558,"passed_time":2.519013431,"remaining_time":1.987271777},
{"learn":[1.491154396],"iteration":559,"passed_time":2.522683206,"remaining_time":1.982108234},
{"learn":[1.488980874],"iteration":560,"passed_time":2.526564989,"remaining_time":1.977115918},
{"learn":[1.487040417],"iteration":561,"passed_time":2.530415304,"remaining_time":1.97210303},
{"learn":[1.482472138],"iteration":562,"passed_time":2.535085249,"remaining_time":1.967730468},
{"learn":[1.480493004],"iteration":563,"passed_time":2.538977659,"remaining_time":1.962755779},
{"learn":[1.480263056],"iteration":564,"passed_time":2.542600435,"remaining_time":1.957577326},
{"learn":[1.47647474],"iteration":565,"passed_time":2.546720607,"remaining_time":1.952785766},
{"learn":[1.473265044],"iteration":566,"passed_time":2.550818652,"remaining_time":1.947979676},
{"learn":[1.470031191],"iteration":567,"passed_time":2.554600951,"remaining_time":1.942935935},
{"learn":[1.467949745],"iteration":568,"passed_time":2.558631229,"remaining_time":1.938084464},
{"learn":[1.466074853],"iteration":569,"passed_time":2.562341544,"remaining_time":1.932994498},
{"learn":[1.463894685],"iteration":570,"passed_time":2.56636973,"remaining_time":1.928148186},
{"learn":[1.461842418],"iteration":571,"passed_time":2.570089149,"remaining_time":1.923073699},
{"learn":[1.459894489],"iteration":572,"passed_time":2.573863008,"remaining_time":1.91804451},
{"learn":[1.458127125],"iteration":573,"passed_time":2.581287891,"remaining_time":1.915729341},
{"learn":[1.456794602],"iteration":574,"passed_time":2.585983605,"remaining_time":1.911379186},
{"learn":[1.452710514],"iteration":575,"passed_time":2.590798877,"remaining_time":1.90711584},
{"learn":[1.452325774],"iteration":576,"passed_time":2.595211722,"remaining_time":1.902555561},
{"learn":[1.449605493],"iteration":577,"passed_time":2.599551578,"remaining_time":1.897942501},
{"learn":[1.449343362],"iteration":578,"passed_time":2.603324235,"remaining_time":1.892917967},
{"learn":[1.444955792],"iteration":579,"passed_time":2.60710749,"remaining_time":1.887905424},
{"learn":[1.443373747],"iteration":580,"passed_time":2.610835884,"remaining_time":1.882857548},
{"learn":[1.443139379],"iteration":581,"passed_time":2.615582987,"remaining_time":1.878545856},
{"learn":[1.441280487],"iteration":582,"passed_time":2.619245352,"remaining_time":1.873456795},
{"learn":[1.440222972],"iteration":583,"passed_time":2.62398374,"remaining_time":1.869139103},
{"learn":[1.436015806],"iteration":584,"passed_time":2.634174342,"remaining_time":1.868687781},
{"learn":[1.43228969],"iteration":585,"passed_time":2.641584851,"remaining_time":1.866239127},
{"learn":[1.429669134],"iteration":586,"passed_time":2.649114239,"remaining_time":1.863857207},
{"learn":[1.42780569],"iteration":587,"passed_time":2.65778389,"remaining_time":1.862256739},
{"learn":[1.427298067],"iteration":588,"passed_time":2.670661102,"remaining_time":1.863568273},
{"learn":[1.425272656],"iteration":589,"passed_time":2.681863541,"remaining_time":1.863667884},
{"learn":[1.422850305],"iteration":590,"passed_time":2.697289341,"remaining_time":1.866652015},
{"learn":[1.419643649],"iteration":591,"passed_time":2.705835419,"remaining_time":1.864832518},
{"learn":[1.417131743],"iteration":592,"passed_time":2.71788573,"remaining_time":1.865395434},
{"learn":[1.412869021],"iteration":593,"passed_time":2.724364352,"remaining_time":1.862107621},
{"learn":[1.410991379],"iteration":594,"passed_time":2.735501089,"remaining_time":1.861979733},
{"learn":[1.409395563],"iteration":595,"passed_time":2.741198989,"remaining_time":1.858128174},
{"learn":[1.407101314],"iteration":596,"passed_time":2.753077756,"remaining_time":1.858442773},
{"learn":[1.406874519],"iteration":597,"passed_time":2.757031759,"remaining_time":1.853389243},
{"learn":[1.403136041],"iteration":598,"passed_time":2.767448867,"remaining_time":1.852666103},
{"learn":[1.400564746],"iteration":599,"passed_time":2.77868296,"remaining_time":1.852455307},
{"learn":[1.396428144],"iteration":600,"passed_time":2.785388107,"remaining_time":1.84920109},
{"learn":[1.392651989],"iteration":601,"passed_time":2.795593478,"remaining_time":1.848249509},
{"learn":[1.390273234],"iteration":602,"passed_time":2.801859447,"remaining_time":1.844673632},
{"learn":[1.386942621],"iteration":603,"passed_time":2.812126786,"remaining_time":1.843712264},
{"learn":[1.383152924],"iteration":604,"passed_time":2.82029804,"remaining_time":1.841351613},
{"learn":[1.381167133],"iteration":605,"passed_time":2.831388055,"remaining_time":1.840869462},
{"learn":[1.379501653],"iteration":606,"passed_time":2.835580717,"remaining_time":1.835886692},
{"learn":[1.376042094],"iteration":607,"passed_time":2.842983433,"remaining_time":1.832976161},
{"learn":[1.375745631],"iteration":608,"passed_time":2.846974927,"remaining_time":1.82786075},
{"learn":[1.374044757],"iteration":609,"passed_time":2.851286435,"remaining_time":1.822953622},
{"learn":[1.371322955],"iteration":610,"passed_time":2.856438475,"remaining_time":1.818583579},
{"learn":[1.3705009],"iteration":611,"passed_time":2.860536122,"remaining_time":1.813542508},
{"learn":[1.369319619],"iteration":612,"passed_time":2.86434611,"remaining_time":1.808322912},
{"learn":[1.366959549],"iteration":613,"passed_time":2.868742316,"remaining_time":1.80347644},
{"learn":[1.365320033],"iteration":614,"passed_time":2.875497448,"remaining_time":1.800108158},
{"learn":[1.362735491],"iteration":615,"passed_time":2.879416009,"remaining_time":1.794960629},
{"learn":[1.358699768],"iteration":616,"passed_time":2.883320832,"remaining_time":1.789808555},
{"learn":[1.356177037],"iteration":617,"passed_time":2.887340818,"remaining_time":1.784731703},
{"learn":[1.355357588],"iteration":618,"passed_time":2.891424533,"remaining_time":1.779697491},
{"learn":[1.353569227],"iteration":619,"passed_time":2.895272974,"remaining_time":1.774522145},
{"learn":[1.35098372],"iteration":620,"passed_time":2.899313895,"remaining_time":1.769468545},
{"learn":[1.349738768],"iteration":621,"passed_time":2.904054433,"remaining_time":1.764843369},
{"learn":[1.347214439],"iteration":622,"passed_time":2.90791595,"remaining_time":1.759685896},
{"learn":[1.346969929],"iteration":623,"passed_time":2.911629054,"remaining_time":1.754443148},
{"learn":[1.344822615],"iteration":624,"passed_time":2.915687125,"remaining_time":1.749412275},
{"learn":[1.344150677],"iteration":625,"passed_time":2.920308251,"remaining_time":1.744720904},
{"learn":[1.342356051],"iteration":626,"passed_time":2.926082172,"remaining_time":1.74071555},
{"learn":[1.34208524],"iteration":627,"passed_time":2.931081633,"remaining_time":1.736245808},
{"learn":[1.339892042],"iteration":628,"passed_time":2.939811731,"remaining_time":1.733974805},
{"learn":[1.33956184],"iteration":629,"passed_time":2.943550329,"remaining_time":1.728751781},
{"learn":[1.338009844],"iteration":630,"passed_time":2.948129667,"remaining_time":1.724025114},
{"learn":[1.336429968],"iteration":631,"passed_time":2.952091662,"remaining_time":1.718939449},
{"learn":[1.333402763],"iteration":632,"passed_time":2.956323266,"remaining_time":1.714013647},
{"learn":[1.331594286],"iteration":633,"passed_time":2.960252547,"remaining_time":1.708915508},
{"learn":[1.329280345],"iteration":634,"passed_time":2.96542864,"remaining_time":1.704537722},
{"learn":[1.326701991],"iteration":635,"passed_time":2.96917331,"remaining_time":1.699338184},
{"learn":[1.324118977],"iteration":636,"passed_time":2.974401926,"remaining_time":1.694988853},
{"learn":[1.319313266],"iteration":637,"passed_time":2.978716923,"remaining_time":1.69011838},
{"learn":[1.315815899],"iteration":638,"passed_time":2.98256655,"remaining_time":1.684986736},
{"learn":[1.313620379],"iteration":639,"passed_time":2.986514156,"remaining_time":1.679914213},
{"learn":[1.312312422],"iteration":640,"passed_time":2.990208175,"remaining_time":1.674703174},
{"learn":[1.310668174],"iteration":641,"passed_time":2.994096155,"remaining_time":1.669605021},
{"learn":[1.309118598],"iteration":642,"passed_time":2.997801014,"remaining_time":1.664408961},
{"learn":[1.305560424],"iteration":643,"passed_time":3.001545838,"remaining_time":1.659239625},
{"learn":[1.303629622],"iteration":644,"passed_time":3.006137576,"remaining_time":1.654540836},
{"learn":[1.302658653],"iteration":645,"passed_time":3.010270122,"remaining_time":1.649590748},
{"learn":[1.300776796],"iteration":646,"passed_time":3.01420999,"remaining_time":1.644538063},
{"learn":[1.299563116],"iteration":647,"passed_time":3.018002461,"remaining_time":1.639408744},
{"learn":[1.297889095],"iteration":648,"passed_time":3.025283048,"remaining_time":1.63617003},
{"learn":[1.297075067],"iteration":649,"passed_time":3.029273558,"remaining_time":1.6311473},
{"learn":[1.29553675],"iteration":650,"passed_time":3.033289778,"remaining_time":1.626141525},
{"learn":[1.292900098],"iteration":651,"passed_time":3.03747579,"remaining_time":1.62122941},
{"learn":[1.29185968],"iteration":652,"passed_time":3.04202537,"remaining_time":1.616512716},
{"learn":[1.289348681],"iteration":653,"passed_time":3.045928734,"remaining_time":1.611454651},
{"learn":[1.286447051],"iteration":654,"passed_time":3.05001165,"remaining_time":1.606494686},
{"learn":[1.282977509],"iteration":655,"passed_time":3.056108034,"remaining_time":1.602593238},
{"learn":[1.279499516],"iteration":656,"passed_time":3.060609267,"remaining_time":1.597852326},
{"learn":[1.279242343],"iteration":657,"passed_time":3.064137522,"remaining_time":1.592606432},
{"learn":[1.276302641],"iteration":658,"passed_time":3.067822634,"remaining_time":1.587446917},
{"learn":[1.273743927],"iteration":659,"passed_time":3.072446081,"remaining_time":1.582775254},
{"learn":[1.271105373],"iteration":660,"passed_time":3.076541637,"remaining_time":1.577833003},
{"learn":[1.269280957],"iteration":661,"passed_time":3.080694102,"remaining_time":1.572922366},
{"learn":[1.26825264],"iteration":662,"passed_time":3.084459701,"remaining_time":1.567817375},
{"learn":[1.266311583],"iteration":663,"passed_time":3.088485473,"remaining_time":1.562848071},
{"learn":[1.265181763],"iteration":664,"passed_time":3.092806456,"remaining_time":1.55803032},
{"learn":[1.263559864],"iteration":665,"passed_time":3.096558785,"remaining_time":1.55292888},
{"learn":[1.261167091],"iteration":666,"passed_time":3.100414194,"remaining_time":1.547882948},
{"learn":[1.258691832],"iteration":667,"passed_time":3.105070102,"remaining_time":1.543238434},
{"learn":[1.256487321],"iteration":668,"passed_time":3.110576764,"remaining_time":1.539014811},
{"learn":[1.255086078],"iteration":669,"passed_time":3.114482135,"remaining_time":1.533998663},
{"learn":[1.252678649],"iteration":670,"passed_time":3.118466294,"remaining_time":1.529024457},
{"learn":[1.251329322],"iteration":671,"passed_time":3.123778397,"remaining_time":1.52470136},
{"learn":[1.249657967],"iteration":672,"passed_time":3.131938717,"remaining_time":1.521759228},
{"learn":[1.248011108],"iteration":673,"passed_time":3.135959779,"remaining_time":1.516799537},
{"learn":[1.245530543],"iteration":674,"passed_time":3.141259359,"remaining_time":1.51245821},
{"learn":[1.245302872],"iteration":675,"passed_time":3.144840868,"remaining_time":1.507290594},
{"learn":[1.245182497],"iteration":676,"passed_time":3.14852585,"remaining_time":1.50217703},
{"learn":[1.24293487],"iteration":677,"passed_time":3.152929572,"remaining_time":1.49740903},
{"learn":[1.240789695],"iteration":678,"passed_time":3.156853269,"remaining_time":1.492415168},
{"learn":[1.238964843],"iteration":679,"passed_time":3.160710485,"remaining_time":1.487393169},
{"learn":[1.236609363],"iteration":680,"passed_time":3.164760458,"remaining_time":1.482464884},
{"learn":[1.235132128],"iteration":681,"passed_time":3.172089377,"remaining_time":1.479068067},
{"learn":[1.234838702],"iteration":682,"passed_time":3.176130072,"remaining_time":1.474133577},
{"learn":[1.233716902],"iteration":683,"passed_time":3.179874029,"remaining_time":1.46906461},
{"learn":[1.232478804],"iteration":684,"passed_time":3.184030717,"remaining_time":1.464189308},
{"learn":[1.232101064],"iteration":685,"passed_time":3.187565451,"remaining_time":1.459031417},
{"learn":[1.228817225],"iteration":686,"passed_time":3.191483163,"remaining_time":1.454052736},
{"learn":[1.226470929],"iteration":687,"passed_time":3.196317469,"remaining_time":1.449492806},
{"learn":[1.224862642],"iteration":688,"passed_time":3.200482148,"remaining_time":1.444629823},
{"learn":[1.222254841],"iteration":689,"passed_time":3.204507803,"remaining_time":1.439706404},
{"learn":[1.219218863],"iteration":690,"passed_time":3.208087437,"remaining_time":1.434586133},
{"learn":[1.217883334],"iteration":691,"passed_time":3.211941969,"remaining_time":1.429592669},
{"learn":[1.216664632],"iteration":692,"passed_time":3.216086499,"remaining_time":1.42473096},
{"learn":[1.214784956],"iteration":693,"passed_time":3.220651458,"remaining_time":1.420056695},
{"learn":[1.214002035],"iteration":694,"passed_time":3.224521495,"remaining_time":1.415077778},
{"learn":[1.213004177],"iteration":695,"passed_time":3.229677115,"remaining_time":1.410663568},
{"learn":[1.210121783],"iteration":696,"passed_time":3.234089701,"remaining_time":1.405924217},
{"learn":[1.209807259],"iteration":697,"passed_time":3.23791173,"remaining_time":1.40093029},
{"learn":[1.206111265],"iteration":698,"passed_time":3.242396631,"remaining_time":1.396225159},
{"learn":[1.204922718],"iteration":699,"passed_time":3.246537764,"remaining_time":1.391373328},
{"learn":[1.202572137],"iteration":700,"passed_time":3.250803222,"remaining_time":1.386576553},
{"learn":[1.201615024],"iteration":701,"passed_time":3.25443406,"remaining_time":1.381511894},
{"learn":[1.198346834],"iteration":702,"passed_time":3.258291464,"remaining_time":1.376547034},
{"learn":[1.196956179],"iteration":703,"passed_time":3.262046167,"remaining_time":1.371542139},
{"learn":[1.194314738],"iteration":704,"passed_time":3.265925565,"remaining_time":1.366592967},
{"learn":[1.192509367],"iteration":705,"passed_time":3.269935392,"remaining_time":1.361701141},
{"learn":[1.190493294],"iteration":706,"passed_time":3.274264016,"remaining_time":1.356943927},
{"learn":[1.190184704],"iteration":707,"passed_time":3.27795553,"remaining_time":1.351925162},
{"learn":[1.188031646],"iteration":708,"passed_time":3.281942082,"remaining_time":1.347031235},
{"learn":[1.186120395],"iteration":709,"passed_time":3.286509935,"remaining_time":1.342377298},
{"learn":[1.18502767],"iteration":710,"passed_time":3.292688674,"remaining_time":1.338378378},
{"learn":[1.184837836],"iteration":711,"passed_time":3.296711284,"remaining_time":1.333501193},
{"learn":[1.183866082],"iteration":712,"passed_time":3.300621304,"remaining_time":1.328581086},
{"learn":[1.182581901],"iteration":713,"passed_time":3.304564225,"remaining_time":1.323676986},
{"learn":[1.179960289],"iteration":714,"passed_time":3.308412638,"remaining_time":1.318737905},
{"learn":[1.178355164],"iteration":715,"passed_time":3.312409077,"remaining_time":1.313860584},
{"learn":[1.17689784],"iteration":716,"passed_time":3.316586662,"remaining_time":1.309057218},
{"learn":[1.174359905],"iteration":717,"passed_time":3.320239938,"remaining_time":1.304049669},
{"learn":[1.173587333],"iteration":718,"passed_time":3.323832319,"remaining_time":1.299022089},
{"learn":[1.172158993],"iteration":719,"passed_time":3.328497935,"remaining_time":1.294415863},
{"learn":[1.170949046],"iteration":720,"passed_time":3.332361593,"remaining_time":1.289499146},
{"learn":[1.169484194],"iteration":721,"passed_time":3.336916607,"remaining_time":1.284851547},
{"learn":[1.16722194],"iteration":722,"passed_time":3.34071491,"remaining_time":1.279914288},
{"learn":[1.166112242],"iteration":723,"passed_time":3.345318889,"remaining_time":1.275287311},
{"learn":[1.165087024],"iteration":724,"passed_time":3.350581453,"remaining_time":1.270910206},
{"learn":[1.16269075],"iteration":725,"passed_time":3.35451661,"remaining_time":1.266029685},
{"learn":[1.160310677],"iteration":726,"passed_time":3.35873119,"remaining_time":1.261256692},
{"learn":[1.159008202],"iteration":727,"passed_time":3.362879772,"remaining_time":1.256460574},
{"learn":[1.157874221],"iteration":728,"passed_time":3.367997782,"remaining_time":1.25202661},
{"learn":[1.157147352],"iteration":729,"passed_time":3.371896046,"remaining_time":1.247139633},
{"learn":[1.155971417],"iteration":730,"passed_time":3.376810669,"remaining_time":1.242629371},
{"learn":[1.153503888],"iteration":731,"passed_time":3.380596939,"remaining_time":1.23770489},
{"learn":[1.151874892],"iteration":732,"passed_time":3.384432656,"remaining_time":1.232801527},
{"learn":[1.150620585],"iteration":733,"passed_time":3.388349532,"remaining_time":1.227930484},
{"learn":[1.14871472],"iteration":734,"passed_time":3.3928125,"remaining_time":1.223258929},
{"learn":[1.146872547],"iteration":735,"passed_time":3.396561051,"remaining_time":1.218331682},
{"learn":[1.143991001],"iteration":736,"passed_time":3.400262807,"remaining_time":1.213390934},
{"learn":[1.142749872],"iteration":737,"passed_time":3.404163651,"remaining_time":1.208524223},
{"learn":[1.140000658],"iteration":738,"passed_time":3.409122558,"remaining_time":1.204033813},
{"learn":[1.137838759],"iteration":739,"passed_time":3.413041045,"remaining_time":1.199176583},
{"learn":[1.136830025],"iteration":740,"passed_time":3.417815905,"remaining_time":1.194621214},
{"learn":[1.1362181],"iteration":741,"passed_time":3.425007643,"remaining_time":1.190905623},
{"learn":[1.13475946],"iteration":742,"passed_time":3.428880236,"remaining_time":1.186032599},
{"learn":[1.133787407],"iteration":743,"passed_time":3.433108469,"remaining_time":1.181284634},
{"learn":[1.132856045],"iteration":744,"passed_time":3.43735359,"remaining_time":1.176543846},
{"learn":[1.13274235],"iteration":745,"passed_time":3.442208167,"remaining_time":1.172011896},
{"learn":[1.131256887],"iteration":746,"passed_time":3.445968818,"remaining_time":1.167108582},
{"learn":[1.130010496],"iteration":747,"passed_time":3.449952667,"remaining_time":1.162283519},
{"learn":[1.129797602],"iteration":748,"passed_time":3.454300081,"remaining_time":1.157582537},
{"learn":[1.128535185],"iteration":749,"passed_time":3.458023857,"remaining_time":1.152674619},
{"learn":[1.127904106],"iteration":750,"passed_time":3.461607033,"remaining_time":1.147723237},
{"learn":[1.126703813],"iteration":751,"passed_time":3.465210148,"remaining_time":1.14278207},
{"learn":[1.124278731],"iteration":752,"passed_time":3.470456829,"remaining_time":1.138383581},
{"learn":[1.122572651],"iteration":753,"passed_time":3.47404299,"remaining_time":1.133441082},
{"learn":[1.121161033],"iteration":754,"passed_time":3.477934647,"remaining_time":1.128601309},
{"learn":[1.119361637],"iteration":755,"passed_time":3.481664717,"remaining_time":1.123711893},
{"learn":[1.118710367],"iteration":756,"passed_time":3.486004513,"remaining_time":1.119021264},
{"learn":[1.115331033],"iteration":757,"passed_time":3.490000374,"remaining_time":1.114221755},
{"learn":[1.112697203],"iteration":758,"passed_time":3.493732406,"remaining_time":1.109340593},
{"learn":[1.11205966],"iteration":759,"passed_time":3.497521055,"remaining_time":1.104480333},
{"learn":[1.109786865],"iteration":760,"passed_time":3.501535697,"remaining_time":1.099693865},
{"learn":[1.107817333],"iteration":761,"passed_time":3.50564727,"remaining_time":1.094939698},
{"learn":[1.106424208],"iteration":762,"passed_time":3.509498629,"remaining_time":1.090106389},
{"learn":[1.104785989],"iteration":763,"passed_time":3.513360948,"remaining_time":1.085279036},
{"learn":[1.102168146],"iteration":764,"passed_time":3.518605524,"remaining_time":1.080878821},
{"learn":[1.101582818],"iteration":765,"passed_time":3.522518676,"remaining_time":1.076069674},
{"learn":[1.09991846],"iteration":766,"passed_time":3.526922371,"remaining_time":1.071411881},
{"learn":[1.097904067],"iteration":767,"passed_time":3.533266963,"remaining_time":1.067341062},
{"learn":[1.097712866],"iteration":768,"passed_time":3.537222949,"remaining_time":1.062546816},
{"learn":[1.095568335],"iteration":769,"passed_time":3.54094318,"remaining_time":1.057684326},
{"learn":[1.093818606],"iteration":770,"passed_time":3.544899101,"remaining_time":1.052894804},
{"learn":[1.091784932],"iteration":771,"passed_time":3.548994582,"remaining_time":1.048148659},
{"learn":[1.090177695],"iteration":772,"passed_time":3.553037663,"remaining_time":1.043388809},
{"learn":[1.088030314],"iteration":773,"passed_time":3.558315185,"remaining_time":1.038991256},
{"learn":[1.086410218],"iteration":774,"passed_time":3.562709822,"remaining_time":1.03433511},
{"learn":[1.085230184],"iteration":775,"passed_time":3.566876091,"remaining_time":1.029613717},
{"learn":[1.082865479],"iteration":776,"passed_time":3.570539919,"remaining_time":1.024749552},
{"learn":[1.081959597],"iteration":777,"passed_time":3.574208459,"remaining_time":1.019889817},
{"learn":[1.079712873],"iteration":778,"passed_time":3.577992011,"remaining_time":1.015065769},
{"learn":[1.078173226],"iteration":779,"passed_time":3.582600093,"remaining_time":1.010476949},
{"learn":[1.076809947],"iteration":780,"passed_time":3.586196051,"remaining_time":1.00560427},
{"learn":[1.075199022],"iteration":781,"passed_time":3.589975547,"remaining_time":1.000786022},
{"learn":[1.073460086],"iteration":782,"passed_time":3.593682991,"remaining_time":0.9959504585},
{"learn":[1.072202899],"iteration":783,"passed_time":3.598209369,"remaining_time":0.9913433977},
{"learn":[1.070446511],"iteration":784,"passed_time":3.602190256,"remaining_time":0.9865871401},
{"learn":[1.070212715],"iteration":785,"passed_time":3.605833266,"remaining_time":0.9817408637},
{"learn":[1.068547211],"iteration":786,"passed_time":3.609814238,"remaining_time":0.9769891139},
{"learn":[1.068367887],"iteration":787,"passed_time":3.614884512,"remaining_time":0.9725323813},
{"learn":[1.067473131],"iteration":788,"passed_time":3.619054551,"remaining_time":0.9678333463},
{"learn":[1.066718916],"iteration":789,"passed_time":3.62300234,"remaining_time":0.9630765714},
{"learn":[1.064600474],"iteration":790,"passed_time":3.628322167,"remaining_time":0.9586843653},
{"learn":[1.062451928],"iteration":791,"passed_time":3.63202982,"remaining_time":0.9538664173},
{"learn":[1.061269226],"iteration":792,"passed_time":3.635788291,"remaining_time":0.949064535},
{"learn":[1.059927228],"iteration":793,"passed_time":3.639705277,"remaining_time":0.9443064069},
{"learn":[1.059301974],"iteration":794,"passed_time":3.645728779,"remaining_time":0.9400935845},
{"learn":[1.05838025],"iteration":795,"passed_time":3.649485165,"remaining_time":0.9352951931},
{"learn":[1.057449143],"iteration":796,"passed_time":3.653276269,"remaining_time":0.9305082592},
{"learn":[1.057335562],"iteration":797,"passed_time":3.657106024,"remaining_time":0.925733605},
{"learn":[1.057225281],"iteration":798,"passed_time":3.660958819,"remaining_time":0.9209671121},
{"learn":[1.055813285],"iteration":799,"passed_time":3.664602242,"remaining_time":0.9161505606},
{"learn":[1.054909609],"iteration":800,"passed_time":3.66895184,"remaining_time":0.9115123798},
{"learn":[1.052522154],"iteration":801,"passed_time":3.672770065,"remaining_time":0.9067437317},
{"learn":[1.051176293],"iteration":802,"passed_time":3.677165935,"remaining_time":0.9021191646},
{"learn":[1.051013891],"iteration":803,"passed_time":3.681439447,"remaining_time":0.8974653379},
{"learn":[1.050593668],"iteration":804,"passed_time":3.688364729,"remaining_time":0.8934548102},
{"learn":[1.048290886],"iteration":805,"passed_time":3.692148837,"remaining_time":0.8886809855},
{"learn":[1.046791018],"iteration":806,"passed_time":3.696115912,"remaining_time":0.8839533718},
{"learn":[1.044834969],"iteration":807,"passed_time":3.699816095,"remaining_time":0.8791642205},
{"learn":[1.044216698],"iteration":808,"passed_time":3.703304297,"remaining_time":0.8743277142},
{"learn":[1.044100863],"iteration":809,"passed_time":3.707219308,"remaining_time":0.8695946524},
{"learn":[1.042834602],"iteration":810,"passed_time":3.711083937,"remaining_time":0.8648518669},
{"learn":[1.041644924],"iteration":811,"passed_time":3.715079469,"remaining_time":0.8601415519},
{"learn":[1.038814202],"iteration":812,"passed_time":3.718807202,"remaining_time":0.8553713983},
{"learn":[1.037518015],"iteration":813,"passed_time":3.723358986,"remaining_time":0.8507921024},
{"learn":[1.03541249],"iteration":814,"passed_time":3.72704232,"remaining_time":0.8460157414},
{"learn":[1.033754636],"iteration":815,"passed_time":3.732376317,"remaining_time":0.8416142675},
{"learn":[1.032292647],"iteration":816,"passed_time":3.736520384,"remaining_time":0.8369439784},
{"learn":[1.028862636],"iteration":817,"passed_time":3.740253544,"remaining_time":0.8321835514},
{"learn":[1.028565772],"iteration":818,"passed_time":3.74479084,"remaining_time":0.827603348},
{"learn":[1.028330393],"iteration":819,"passed_time":3.749064953,"remaining_time":0.8229654776},
{"learn":[1.026474166],"iteration":820,"passed_time":3.754578179,"remaining_time":0.8185986529},
{"learn":[1.025263957],"iteration":821,"passed_time":3.758235829,"remaining_time":0.8138272234},
{"learn":[1.023869377],"iteration":822,"passed_time":3.762377055,"remaining_time":0.8091625016},
{"learn":[1.023703432],"iteration":823,"passed_time":3.768784456,"remaining_time":0.8049830877},
{"learn":[1.021646326],"iteration":824,"passed_time":3.773343464,"remaining_time":0.8004061892},
{"learn":[1.021312831],"iteration":825,"passed_time":3.777730724,"remaining_time":0.7957931549},
{"learn":[1.019215047],"iteration":826,"passed_time":3.781644875,"remaining_time":0.7910816969},
{"learn":[1.018314689],"iteration":827,"passed_time":3.785951623,"remaining_time":0.7864537187},
{"learn":[1.018203876],"iteration":828,"passed_time":3.789876919,"remaining_time":0.7817478325},
{"learn":[1.018119711],"iteration":829,"passed_time":3.793381047,"remaining_time":0.7769575638},
{"learn":[1.015630461],"iteration":830,"passed_time":3.797134704,"remaining_time":0.7722211371},
{"learn":[1.014520033],"iteration":831,"passed_time":3.801630288,"remaining_time":0.7676368851},
{"learn":[1.012971691],"iteration":832,"passed_time":3.806450999,"remaining_time":0.7631180274},
{"learn":[1.011910115],"iteration":833,"passed_time":3.81041815,"remaining_time":0.7584285527},
{"learn":[1.010311573],"iteration":834,"passed_time":3.814247778,"remaining_time":0.7537136327},
{"learn":[1.008539114],"iteration":835,"passed_time":3.818690045,"remaining_time":0.7491210136},
{"learn":[1.006763074],"iteration":836,"passed_time":3.822825969,"remaining_time":0.7444690955},
{"learn":[1.006314475],"iteration":837,"passed_time":3.826536528,"remaining_time":0.7397361784},
{"learn":[1.005285185],"iteration":838,"passed_time":3.830444165,"remaining_time":0.7350435167},
{"learn":[1.004652652],"iteration":839,"passed_time":3.835615773,"remaining_time":0.7305934805},
{"learn":[1.003440304],"iteration":840,"passed_time":3.839729025,"remaining_time":0.7259416349},
{"learn":[1.002413516],"iteration":841,"passed_time":3.843359871,"remaining_time":0.7212005458},
{"learn":[1.000971532],"iteration":842,"passed_time":3.847561466,"remaining_time":0.7165683869},
{"learn":[0.9998868541],"iteration":843,"passed_time":3.851502023,"remaining_time":0.7118889995},
{"learn":[0.9986139601],"iteration":844,"passed_time":3.855112197,"remaining_time":0.707150758},
{"learn":[0.9965923889],"iteration":845,"passed_time":3.859055778,"remaining_time":0.7024758745},
{"learn":[0.9938944754],"iteration":846,"passed_time":3.863163273,"remaining_time":0.6978323268},
{"learn":[0.9930992863],"iteration":847,"passed_time":3.868465504,"remaining_time":0.6934041941},
{"learn":[0.9920162279],"iteration":848,"passed_time":3.872142223,"remaining_time":0.6886848949},
{"learn":[0.9905608785],"iteration":849,"passed_time":3.876199451,"remaining_time":0.6840351973},
{"learn":[0.989523965],"iteration":850,"passed_time":3.880371601,"remaining_time":0.6794070136},
{"learn":[0.9889579098],"iteration":851,"passed_time":3.885126468,"remaining_time":0.6748811235},
{"learn":[0.9871441175],"iteration":852,"passed_time":3.888873572,"remaining_time":0.670181026},
{"learn":[0.9869431532],"iteration":853,"passed_time":3.892494136,"remaining_time":0.6654615267},
{"learn":[0.9853651592],"iteration":854,"passed_time":3.899051479,"remaining_time":0.6612426484},
{"learn":[0.9841895778],"iteration":855,"passed_time":3.903175917,"remaining_time":0.6566090327},
{"learn":[0.9834042651],"iteration":856,"passed_time":3.906849702,"remaining_time":0.6519014089},
{"learn":[0.9823286725],"iteration":857,"passed_time":3.910770037,"remaining_time":0.6472369991},
{"learn":[0.9814060212],"iteration":858,"passed_time":3.914601844,"remaining_time":0.6425597904},
{"learn":[0.9812871543],"iteration":859,"passed_time":3.91827442,"remaining_time":0.6378586265},
{"learn":[0.980802313],"iteration":860,"passed_time":3.922610247,"remaining_time":0.6332669272},
{"learn":[0.9790450298],"iteration":861,"passed_time":3.926708665,"remaining_time":0.6286378142},
{"learn":[0.978484376],"iteration":862,"passed_time":3.930405787,"remaining_time":0.6239462258},
{"learn":[0.9765898631],"iteration":863,"passed_time":3.934297556,"remaining_time":0.6192875783},
{"learn":[0.9755539717],"iteration":864,"passed_time":3.938216456,"remaining_time":0.6146349382},
{"learn":[0.9741626503],"iteration":865,"passed_time":3.943959791,"remaining_time":0.6102662957},
{"learn":[0.973072651],"iteration":866,"passed_time":3.947857861,"remaining_time":0.6056114135},
{"learn":[0.9718559923],"iteration":867,"passed_time":3.951640878,"remaining_time":0.6009407787},
{"learn":[0.970949039],"iteration":868,"passed_time":3.955508699,"remaining_time":0.5962849708},
{"learn":[0.9687464439],"iteration":869,"passed_time":3.959943329,"remaining_time":0.5917156699},
{"learn":[0.9672000563],"iteration":870,"passed_time":3.963793845,"remaining_time":0.5870601677},
{"learn":[0.9665190945],"iteration":871,"passed_time":3.967421123,"remaining_time":0.5823737428},
{"learn":[0.9652729242],"iteration":872,"passed_time":3.971305704,"remaining_time":0.5777271757},
{"learn":[0.9626857433],"iteration":873,"passed_time":3.975597425,"remaining_time":0.5731410475},
{"learn":[0.9605904051],"iteration":874,"passed_time":3.979672629,"remaining_time":0.5685246613},
{"learn":[0.9591998378],"iteration":875,"passed_time":3.983339313,"remaining_time":0.5638516836},
{"learn":[0.9570885911],"iteration":876,"passed_time":3.987580007,"remaining_time":0.5592615061},
{"learn":[0.9550700731],"iteration":877,"passed_time":3.99176458,"remaining_time":0.5546643266},
{"learn":[0.9538362796],"iteration":878,"passed_time":3.995532631,"remaining_time":0.550010749},
{"learn":[0.9523769235],"iteration":879,"passed_time":4.000636429,"remaining_time":0.5455413313},
{"learn":[0.9522434896],"iteration":880,"passed_time":4.012728524,"remaining_time":0.542014409},
{"learn":[0.9513790857],"iteration":881,"passed_time":4.016461892,"remaining_time":0.5373497769},
{"learn":[0.9506375743],"iteration":882,"passed_time":4.020293196,"remaining_time":0.5327002309},
{"learn":[0.9496121454],"iteration":883,"passed_time":4.024077273,"remaining_time":0.5280463391},
{"learn":[0.9472125183],"iteration":884,"passed_time":4.028084606,"remaining_time":0.5234234233},
{"learn":[0.9459072791],"iteration":885,"passed_time":4.031889558,"remaining_time":0.5187758574},
{"learn":[0.9450048503],"iteration":886,"passed_time":4.036506219,"remaining_time":0.5142335995},
{"learn":[0.9449132234],"iteration":887,"passed_time":4.040268366,"remaining_time":0.5095833975},
{"learn":[0.9440612608],"iteration":888,"passed_time":4.044128618,"remaining_time":0.5049474428},
{"learn":[0.9419966936],"iteration":889,"passed_time":4.048193401,"remaining_time":0.5003385102},
{"learn":[0.9396926279],"iteration":890,"passed_time":4.052765884,"remaining_time":0.4957929084},
{"learn":[0.938141828],"iteration":891,"passed_time":4.056804933,"remaining_time":0.49118266},
{"learn":[0.9364466429],"iteration":892,"passed_time":4.060409309,"remaining_time":0.4865216081},
{"learn":[0.9360397597],"iteration":893,"passed_time":4.064205743,"remaining_time":0.4818856921},
{"learn":[0.9359286797],"iteration":894,"passed_time":4.068101449,"remaining_time":0.4772632985},
{"learn":[0.9350415671],"iteration":895,"passed_time":4.072007492,"remaining_time":0.4726437267},
{"learn":[0.9339792753],"iteration":896,"passed_time":4.076239376,"remaining_time":0.4680631614},
{"learn":[0.9334720149],"iteration":897,"passed_time":4.0798466,"remaining_time":0.4634124201},
{"learn":[0.9324275694],"iteration":898,"passed_time":4.083986081,"remaining_time":0.4588237978},
{"learn":[0.9310837244],"iteration":899,"passed_time":4.089245114,"remaining_time":0.4543605682},
{"learn":[0.9303935608],"iteration":900,"passed_time":4.093152368,"remaining_time":0.4497470416},
{"learn":[0.9294765582],"iteration":901,"passed_time":4.096957828,"remaining_time":0.4451240213},
{"learn":[0.9278376538],"iteration":902,"passed_time":4.101266513,"remaining_time":0.440556868},
{"learn":[0.9266840208],"iteration":903,"passed_time":4.10534902,"remaining_time":0.4359662677},
{"learn":[0.9255036553],"iteration":904,"passed_time":4.10933904,"remaining_time":0.4313670815},
{"learn":[0.9234353985],"iteration":905,"passed_time":4.113208805,"remaining_time":0.4267567634},
{"learn":[0.92118807],"iteration":906,"passed_time":4.119695037,"remaining_time":0.4224163599},
{"learn":[0.9192298601],"iteration":907,"passed_time":4.123539744,"remaining_time":0.4178035864},
{"learn":[0.9188147991],"iteration":908,"passed_time":4.127218757,"remaining_time":0.4131759152},
{"learn":[0.9178206989],"iteration":909,"passed_time":4.13156976,"remaining_time":0.4086167895},
{"learn":[0.9168385177],"iteration":910,"passed_time":4.135893917,"remaining_time":0.404055498},
{"learn":[0.9163013968],"iteration":911,"passed_time":4.140802361,"remaining_time":0.399551105},
{"learn":[0.9155196249],"iteration":912,"passed_time":4.144961762,"remaining_time":0.3949744505},
{"learn":[0.9148330076],"iteration":913,"passed_time":4.149369459,"remaining_time":0.3904220716},
{"learn":[0.9145413813],"iteration":914,"passed_time":4.153098351,"remaining_time":0.3858069506},
{"learn":[0.9130390779],"iteration":915,"passed_time":4.156862558,"remaining_time":0.3811970031},
{"learn":[0.9119797568],"iteration":916,"passed_time":4.161040339,"remaining_time":0.3766263338},
{"learn":[0.9113323687],"iteration":917,"passed_time":4.16512576,"remaining_time":0.3720482705},
{"learn":[0.9097563279],"iteration":918,"passed_time":4.169139628,"remaining_time":0.3674649726},
{"learn":[0.9082246683],"iteration":919,"passed_time":4.172855441,"remaining_time":0.3628569948},
{"learn":[0.9065853387],"iteration":920,"passed_time":4.176768584,"remaining_time":0.3582678807},
{"learn":[0.9048104061],"iteration":921,"passed_time":4.180835445,"remaining_time":0.3536932372},
{"learn":[0.9042987956],"iteration":922,"passed_time":4.184542334,"remaining_time":0.3490896639},
{"learn":[0.9037254992],"iteration":923,"passed_time":4.188491578,"remaining_time":0.3445079653},
{"learn":[0.9024160736],"iteration":924,"passed_time":4.193807535,"remaining_time":0.3400384488},
{"learn":[0.9015399478],"iteration":925,"passed_time":4.197698566,"remaining_time":0.3354532331},
{"learn":[0.9003112071],"iteration":926,"passed_time":4.201352233,"remaining_time":0.3308508231},
{"learn":[0.8984155179],"iteration":927,"passed_time":4.205330921,"remaining_time":0.3262756749},
{"learn":[0.8961842976],"iteration":928,"passed_time":4.209229879,"remaining_time":0.3216957173},
{"learn":[0.8944576385],"iteration":929,"passed_time":4.212912607,"remaining_time":0.3171009489},
{"learn":[0.8937767615],"iteration":930,"passed_time":4.216782927,"remaining_time":0.3125220429},
{"learn":[0.8926323949],"iteration":931,"passed_time":4.220465204,"remaining_time":0.3079309376},
{"learn":[0.8913892576],"iteration":932,"passed_time":4.226421613,"remaining_time":0.303505089},
{"learn":[0.890274557],"iteration":933,"passed_time":4.230072379,"remaining_time":0.2989130375},
{"learn":[0.8896885424],"iteration":934,"passed_time":4.234409031,"remaining_time":0.2943706813},
{"learn":[0.8878690542],"iteration":935,"passed_time":4.242463999,"remaining_time":0.2900830085},
{"learn":[0.887392358],"iteration":936,"passed_time":4.247459407,"remaining_time":0.2855815823},
{"learn":[0.8866868203],"iteration":937,"passed_time":4.254095234,"remaining_time":0.2811875314},
{"learn":[0.886359103],"iteration":938,"passed_time":4.258246691,"remaining_time":0.2766273143},
{"learn":[0.8853005556],"iteration":939,"passed_time":4.262119778,"remaining_time":0.2720501986},
{"learn":[0.88460553],"iteration":940,"passed_time":4.265996632,"remaining_time":0.2674748154},
{"learn":[0.8844866651],"iteration":941,"passed_time":4.26960961,"remaining_time":0.2628846681},
{"learn":[0.8836304975],"iteration":942,"passed_time":4.273891183,"remaining_time":0.2583370068},
{"learn":[0.882561774],"iteration":943,"passed_time":4.27769809,"remaining_time":0.2537617511},
{"learn":[0.8815178136],"iteration":944,"passed_time":4.281297163,"remaining_time":0.2491760253},
{"learn":[0.8804319687],"iteration":945,"passed_time":4.285048823,"remaining_time":0.2446010956},
{"learn":[0.878626624],"iteration":946,"passed_time":4.289222701,"remaining_time":0.2400515345},
{"learn":[0.8779360142],"iteration":947,"passed_time":4.293216477,"remaining_time":0.2354928869},
{"learn":[0.8763498803],"iteration":948,"passed_time":4.297062458,"remaining_time":0.2309274872},
{"learn":[0.8753294408],"iteration":949,"passed_time":4.301033159,"remaining_time":0.2263701663},
{"learn":[0.8750977675],"iteration":950,"passed_time":4.305011367,"remaining_time":0.2218144658},
{"learn":[0.8746893697],"iteration":951,"passed_time":4.308752602,"remaining_time":0.2172480303},
{"learn":[0.8740027313],"iteration":952,"passed_time":4.312649775,"remaining_time":0.2126910172},
{"learn":[0.8730785806],"iteration":953,"passed_time":4.316472885,"remaining_time":0.2081318163},
{"learn":[0.8716061258],"iteration":954,"passed_time":4.32071228,"remaining_time":0.2035937723},
{"learn":[0.8697864038],"iteration":955,"passed_time":4.324731373,"remaining_time":0.1990462138},
{"learn":[0.8690083717],"iteration":956,"passed_time":4.330690052,"remaining_time":0.1945869093},
{"learn":[0.8678961612],"iteration":957,"passed_time":4.334181513,"remaining_time":0.1900163085},
{"learn":[0.866537461],"iteration":958,"passed_time":4.338806176,"remaining_time":0.1854964059},
{"learn":[0.8659977858],"iteration":959,"passed_time":4.342435464,"remaining_time":0.180934811},
{"learn":[0.86544535],"iteration":960,"passed_time":4.346126021,"remaining_time":0.1763776429},
{"learn":[0.8646249885],"iteration":961,"passed_time":4.350084767,"remaining_time":0.1718328702},
{"learn":[0.8645394076],"iteration":962,"passed_time":4.355508969,"remaining_time":0.1673456198},
{"learn":[0.8636992712],"iteration":963,"passed_time":4.359335587,"remaining_time":0.1627967647},
{"learn":[0.8621032086],"iteration":964,"passed_time":4.363211325,"remaining_time":0.1582511879},
{"learn":[0.8613883735],"iteration":965,"passed_time":4.366715796,"remaining_time":0.1536939307},
{"learn":[0.8612559315],"iteration":966,"passed_time":4.371908795,"remaining_time":0.1491964739},
{"learn":[0.8607781076],"iteration":967,"passed_time":4.375832867,"remaining_time":0.144655632},
{"learn":[0.8594672691],"iteration":968,"passed_time":4.379939494,"remaining_time":0.1401219033},
{"learn":[0.8580087632],"iteration":969,"passed_time":4.384110005,"remaining_time":0.1355910311},
{"learn":[0.856469895],"iteration":970,"passed_time":4.387955417,"remaining_time":0.1310511917},
{"learn":[0.85524028],"iteration":971,"passed_time":4.391631873,"remaining_time":0.126507914},
{"learn":[0.8528121695],"iteration":972,"passed_time":4.395710847,"remaining_time":0.1219775878},
{"learn":[0.8513478023],"iteration":973,"passed_time":4.400211562,"remaining_time":0.1174594462},
{"learn":[0.8512558181],"iteration":974,"passed_time":4.403798204,"remaining_time":0.1129179027},
{"learn":[0.8499322846],"iteration":975,"passed_time":4.40810085,"remaining_time":0.1083959225},
{"learn":[0.8498274148],"iteration":976,"passed_time":4.411845207,"remaining_time":0.1038612485},
{"learn":[0.8497687871],"iteration":977,"passed_time":4.416047745,"remaining_time":0.09933849733},
{"learn":[0.8481997895],"iteration":978,"passed_time":4.419817599,"remaining_time":0.09480711909},
{"learn":[0.8480984457],"iteration":979,"passed_time":4.423409969,"remaining_time":0.09027367283},
{"learn":[0.8473464204],"iteration":980,"passed_time":4.427112681,"remaining_time":0.0857442823},
{"learn":[0.8457698301],"iteration":981,"passed_time":4.431187732,"remaining_time":0.08122340039},
{"learn":[0.8444925284],"iteration":982,"passed_time":4.435279774,"remaining_time":0.07670371939},
{"learn":[0.8424079822],"iteration":983,"passed_time":4.439111805,"remaining_time":0.07218067975},
{"learn":[0.841654372],"iteration":984,"passed_time":4.443054323,"remaining_time":0.06766072574},
{"learn":[0.8400446885],"iteration":985,"passed_time":4.447063559,"remaining_time":0.06314289029},
{"learn":[0.8389391485],"iteration":986,"passed_time":4.450813771,"remaining_time":0.05862267378},
{"learn":[0.8373850983],"iteration":987,"passed_time":4.454785581,"remaining_time":0.05410670746},
{"learn":[0.8363126847],"iteration":988,"passed_time":4.458438488,"remaining_time":0.04958829461},
{"learn":[0.8346873195],"iteration":989,"passed_time":4.462785012,"remaining_time":0.04507863649},
{"learn":[0.8341372276],"iteration":990,"passed_time":4.466470262,"remaining_time":0.04056330207},
{"learn":[0.8332132158],"iteration":991,"passed_time":4.470553934,"remaining_time":0.0360528543},
{"learn":[0.832465531],"iteration":992,"passed_time":4.474812941,"remaining_time":0.0315445021},
{"learn":[0.8313652213],"iteration":993,"passed_time":4.480944442,"remaining_time":0.02704795438},
{"learn":[0.8303225745],"iteration":994,"passed_time":4.484596827,"remaining_time":0.02253566245},
{"learn":[0.8302333924],"iteration":995,"passed_time":4.486031481,"remaining_time":0.01801619069},
{"learn":[0.8291956785],"iteration":996,"passed_time":4.490059896,"remaining_time":0.01351071182},
{"learn":[0.8284695349],"iteration":997,"passed_time":4.494258415,"remaining_time":0.009006529889},
{"learn":[0.8271842066],"iteration":998,"passed_time":4.497994209,"remaining_time":0.004502496706},
{"learn":[0.8265072052],"iteration":999,"passed_time":4.502743707,"remaining_time":0}
]}